Workbook
Name NamedRange1: 'JON EVENTS'!$C:$C
Name NamedRange1: EVENTS!$C:$C

Sheet GLOSSARY
A1: PERSON ID | B1: NAME | C1: OTHER NAMES | D1: ETHNICITY/NATIONALITY | E1: PHYSICAL DESCRIPTORS | F1: LOCATION(S) | G1: LOCATION IDS | H1: BIOGRAPHICAL INFORMATION
A2: P1 | B2: MOLIA | C2: COOBAH CUBBAH | D2: EBO | E2: 4'6 INCHES HIGH (1761) 'TT' IN DOWNWARD TRIANGLE BRAND ON HER RIGHT SHOULDER (1761) BRAND ON HER FOREHEAD (1770) CHAIN/COLLAR MARKS AND SCARS ON HER NECK/SHOULDERS SCARS FROM REPEATED FLOGGINGS | F2: EGYPT ESTATE (1761-1767) BREADNUT ISLAND PEN (1767-1774) | G2: L1; L3 | H2: Molia first appeared in the diary in December of 1761. Thistlewood purchased her in a group sale of five other Africans from a trader for 50 pounds. Upon her arrival to Egypt estate, he paired her with an enslaved fieldwoman named Wonga (also known as Princess) to be 'seasoned'. One week after her purchase, he put her to work in Egypt's fields. Four years following her purchase, Molia gave birth to a mixed race baby girl named Silvia. When Silvia was fifteen months old, Thistlewood hired Molia to labor on Masemure, a neighboring sugar plantation. He forced her to leave Silvia behind and in the care of Nanny, another enslaved mother of a little girl named Little Phibbah who was the same age as Silvia. Shortly after their separation, Silvia fell sick and died. Molia was never the same following Silvia's death. She never had any more children, and and she also refused to stay in place. Over the course of the next six years, she would run away no less than fourteen times. The seventh of these escapes was to a place called Bluefields Bay, to see a person Molia herself identified as a "Shipmate," a person who had survived the Middle Passage voyage with her to Jamaica. The fourteenth of these escapes (and the last that she would make in Jamaica) was to an estate called Paradise; it was the same estate where Molia had been sent to give birth to Silvia. Following this fourteenth recapture, Thistlewood sold Molia to another slave owner, who transported her away from Jamaica, and to the British colony of Savannah. Georgia.
A3: P2 | B3: SILVIA | D3: HALF EBO MOST LIKELY MIXED RACE | E3: FAIRSKINNED;'MULATTO' (1766) | F3: EGYPT ESTATE (1766) BREADNUT ISLAND PEN (1767-1768) | G3: L1; L3 | H3: Silvia was born on November 12, 1766. Her mother was Molia, an "Ebo" woman presumed to have been 15 at the time of her capture into the slave trade, and 20 at the time of her birth. Silvia's father was never identified, although he was presumed by Thistlewood to have been a white man. Her mother was assisted in the delivery by an enslaved grannie named Paradise Quasheba. For the first fifteen months of her life Silvia lived with her mother, and another enslaved young African woman named Peggy. In the winter of 1768, Thistlewood contracted Molia out to labor on a neighboring sugar estate named Masemure. He forced Molia to leave Silvia behind and in the care of another enslaved woman named Nanny, who also had a 1 year old daughter named Little Phibbah. Several months after her mother's departure, Silvia became sick of an unknown illness, and died at just fifteen months old.
A4: P3 | B4: EGYPT LUCY | D4: ? | F4: EGYPT ESTATE (1750-1772) | G4: L1 | H4: Egypt Lucy was an Afro-Creole woman who labored on Egypt Estate's First gang for much of her life. She had two primary domestic partners: Daniel, a skilled enslaved laborer who lived on Egypt, and Mason Quashe a skilled enslaved laborer who belonged to Elizabeth Anderson--the quadroon mistress of William Dorrill, Thistlewood's first employer-- and who was a regular visitor at Egypt to perform various tasks of carpentry, masonry, and even supervision of the First Gang. Between 1750 and her death in 1772, Egypt Lucy had three confirmed pregnancies: one in October 1754 to her daughter Julina with Daniel, the second in August of 1758 to an unnamed son (presumably also with Daniel) who died at just 5 days old, and the third in November of 1759 to a son who was named Little Quashe (presumably after his father, Mason Quashe). In May 1760, Egypt became the wet nurse to John, the son of Egypt's housekeeper and Thistlewood. This seemed to mark the beginining of a strong and lasting friendship between not only Egypt Lucy and Phibbah, but between Egypt Lucy and Phibbah's broader social network of enslaved domestic workers. This circle included Phibbah's sister, Nancy,her daughter Accubah, an enslaved healer woman named Vine, and another enslaved domestic worker called House Franke. Together, the six women formed an agricutural co-op of sorts, pooling the money and resources they earned through the selling of goods they raised from their provison grounds, their raising of livestock, and from sewing work they were contracted to perform for whites. They intended the funds to be used to purchase at least one of each other's freedom. Egypt Lucy was relatively prosperous as a enslaved business woman; such that in 1769, she along with Phibbah, and House Franke gave Thistlewood a 27 pound loan to help him in his transition from Egypt's overseer to an independeny penkeeper of a property called Breadnut Island Pen. EGypt Lucy would als give Thistlewood a second personal loan of 10 pounds; he would go on to repay both loans within about a year. Following her stint as John's wetnurse, Egypt Lucy continued to act as a care provider and parental influence for both Phibbah's children. When Phibbah and Thistlewood moved away from Egypt and left John behind, they entrusted EGypt Lucy to escort him to their newhome on Breadnut Islabd Pen for visits. Egypt Lucy also kept abreast of the day-to-day and night-to-night activities of Phibbah's daughter Accubah--including her covert fasincination and involvement in the secret Myal society. On multiple occasions throughout the years, Egypt Lucy was chosen by her white masters to be a 'seasoner,' a role designed for mostly Afro-Creole enslaved men and women who had either been born or resided in Jamaica for extended periods of time to acclimate/'season' newly arrived Africans to their new realities. In December of 1761, after purchasing 6 new Africans from a slave trader named John Hutt, Thistlewood tasked Egpyt Lucy with being the seasoner of a young African girl included in this sale named Ogo (he would rename her Maria). In November of 1766, Ogo would give birth to her first child: a daughter named Lucy. In July 1770, shortly following Molia's fourth escape from and return to Breadnut Island Pen, Egypt Lucy paid a visit to the pen, where she interrupted Thistlewood's attempt to punish Molia by confining her to a set of bilboes, convincing him not to. As a field laborer, Egypt Lucy was frequently in poor health. In June of 1772, she died. Phibbah and a 12 year old John attended her funeral and burial.
A5: P4 | B5: JULINA | D5: ? | F5: EGYPT ESTATE (1750--?) | G5: L1 | H5: Julina was born in October of 1754 on Egypt Estate. Her mother was Egypt Lucy, an enslaved and Afro-Creole member Egypt estate's first gang. Her father was Daniel, an enslaved skilled laborer who also lived on Egypt. In August of 1758, Julina's mother Egypt Lucy gave birth to an unnamed baby boy, Julina's brother, who died at 5 days old. The following year, in November of 1759, Egypt Lucy was sent away from Egypt to a neighboring estate called Paradise, where she gave birth to another son, Julina's second brother, who was named Little Quashe. Julina fell sick while her mother was away, but soon recovered. Little Quashe and Egypt Lucy returned to Egypt in January of 1760, where they would continue as one nuclear household. In October of 1766, Julina would, for reasons unspecified by Thistlewood, accompany Molia to Paradise for her lying in period before she gave birth to Silvia in November of that same year. In December of 1770, Julina became the mistress/concubine of a white man named Robert Parker, a friend of Thistlewood's.
A6: P5 | B6: LITTLE QUASHE | D6: ? | F6: EGYPT ESTATE (1759--?) | G6: L1 | H6: Little Quashe was born in November of 1759, the son of Egypt Lucy, a field laborer of Egypt Estate and Mason Quashe, a skilled enslaved laborer who belonged to Elizabeth Anderson--the quadroon mistress of William Dorrill, Thistlewood's first employer-- and who was a regular visitor at Egypt to perform various tasks of carpentry, masonry, and even supervision of the First Gang. He was half-brother to Julina, Egypt Lucy's first daughter. Like many children of his time and place, Little Quashe was frequently ill. He was cared for by his mother, as well as by his mother's close friends, Phibbah (the housekeeper of Egypt Estate), and Vine, an enslaved woman, healer and storyteller from a neighboring estate.
A7: P6 | B7: ABBA | D7: AFRICAN | F7: EGYPT ESTATE (1758--1767) BREADNUT ISLAND PEN (1767-1786) | G7: L1; L3 | H7: Abba was an enslaved African young woman, first appearing in the diary in Februaryof 1758 when she was purchased by Thistlewood from a slave trader named John Parkinson for 46 pounds. Thistlewood intended for her to be a domestic worker, setting her to train in the cookroom with Egypt's housekeeper Phibbah, then hiring her out to other white neighbors throughout the parish. Abba would have several domestic/sexual partners over the course of the twenty eight years she appears in the diaries. The first of these was Hazat, a driver who belonged to William Mould, an owner of a neighboring plantation. Another was Cudjoe, an enslaved fieldhand who belonged to John Rickett, one of Thistlewood's friends. A third was Neptune, an enslaved man who belonged to a Savanna la Mar tavern owner and another of Thistlewood's friends, Thomas Emotson. A fourth was Lincoln, the very first enslaved person Thistlewood ever purcahsed. Abba was unique among the many enslaved women who appear in the diairies in the sense that was extremely fertile, having a total of thirteen pregnancies over the span of twenty eight years. Ten of these resulted in live births, one in a stillbirth. Of these ten children, six (Including Johnie, Neptune, Jenny, Mary)survived their first year of life and four survived until at least 1786, the year of Thistlewood's death and the last year of the diary records. Abba and her children's living arrangements fluctuated usually depending upon who her current sexual/domestic partner was, but for a period of time in 1767, she and Mary, Johnie and Neptune lived with Sally, a Congo woman who Thistlewood had first purchased as a 8 or 9 year old child in 1762. Abba was known to tell the Anansi spider stories that she had learned from her homeland alongside Vine, an enslaved domestic woman and healer from a neighboring plantation called Cabaritta Estate. Abba would be one of the enslaved people on Breadnut Island Pen who would go on to outlive Thistlewood following his death in 1786. In a 1787 appraisal of his human property, her age was described as "unknown", and she was valued at 40 pounds.
A8: P7 | B8: PHIBBAH | C8: PHIB; PHIBBAH | D8: ? | F8: EGYPT ESTATE (?--1767) PARADISE ESTATE SALT RIVER ESTATE BREADNUT ISLAND PEN (1767-1786) | G8: L1; L2; L3; L4 | H8: Phibbah was the Afro-Creole housekeeper of Egypt Estate. She was owned by Molly Cope, the wife of John Cope, Thistlewood's employer. A prominent and influential figure among the broader enslaved communit, Phibbah often leveraged that influence to gain relative material and social benefits for herself, her children and her other loved ones. Phibbah was very close with a sister named Nancy who lived on a neighboring plantation and very frequently visited her. Phibbah had an unnamed enslaved husband, but this relationship was soon displaced by the sexual/domestic relationship she would strike up with Thistlewood that would last for over three decades, ending only in his death in 1786. Although he was never monogamous, Thistlewood referred to Phibbah as his "wife". The diaries depict Phibbah as having three confirmed pregnancies/children. The first was a daughter named Accubah [unknown date of birth and father; also called Coobah and later Jenny Young], a stillborn boy [with John Cope, born ] and John [her son with Thistlewood who lived to the age of 20]. Phibbah had a tight knit circle of friends, most of whom were enslaved women domestic laborers. These included her sister Nancy, her daughter Accubah, domestic laborer and healer Vine, and domestic laborer House Franke. Following the birth of her son John in 1760, she also became very close friends with an enslaved field woman of Egypt estate called Egypt Lucy who served as John's wetnurse. Phibbah often visited with Egypt Lucy, cared for her son Little Quashe when he was will. She also brought Egypt Lucy into the agricultural co-op network that she had formed with her sister, daughter and other friends. Together, the six women pooled the money and resources they earned through the selling of goods they raised from their provison grounds, their raising of livestock, and from sewing work they were contracted to perform for whites. They intended the funds to be used to purchase at least one of each other's freedom. Phibbah was a very prosperous businesswoman and in 1769, she along with Egypt Lucy, and House Franke gave Thistlewood a 27 pound loan to help him in his transition from Egypt's overseer to an independent penkeeper of a property called Breadnut Island Pen-- a loan that he would return about a year or so later. It was one of several loans she would give to them him throughout their relationship. Phibbah outlived Thistlewood, and was granted her freedom following his death in 1786.
A9: P8 | B9: NANCY | D9: ? | F9: PARADISE ESTATE (1750-1786) | G9: L2 | H9: Nancy was an Afro-Creole domestic laborer who lived on/moved between Egypt estate, as well as Paradise estate (another plantation owned by John Cope. She was the sister of Phibbah, Egypt's housekeeper, and aunt to Phibbah's two children, Accubah [also known as Coobah and later Jenny Young] and John. The diaries confirm Nancy as having two pregnancies; one in to a boy named Davie who fell sick snd died in 1756, and another in 1757 to a girl who was born dead. Like Phibbah, Nancy held relative measures of material and social privilege. She held multiple 'balls' that her sister and other domestic enslaved labrers and whites attended. She was able to 'rent' out the labor of an enslaved Egypt fieldwoman named Rose to assist her in caring for Davie when he was ill. In the aftermath of Davie's death, Nancy held a "play" (funeral) for Davie that lasted for two days/nights. Nancy was close friends with her sister Phibbah, as well as a broader circle of friends that included ncluded her sister Phibbah, her niece Accubah, domestic laborer and healer Vine, domestic laborer House Franke, and fieldwoman Egypt Lucy. Together, the six women pooled the money and resources they earned through the selling of goods they raised from their provison grounds, their raising of livestock, and from sewing work they were contracted to perform for whites. They intended the funds to be used to purchase at least one of each other's freedom (notably, Nancy's).
A10: P9 | B10: JOHN | C10: MULATTO JOHN PHIBBAH'S JOHN | D10: MIXED RACE | E10: FAIR SKINNED; 'MULATTO' | F10: EGYPT ESTATE (1760) MRS BENNETT'S | G10: L1; L18 | H10: John was the mixed race son of Phibbah, the housekeeper of Egypt Estate, and Thomas Thistlewood, Egypt's overseer and the later owner of Breadnut Island Pen. Although he assumed paternal and financial support for him, Thistlewood never directly acknowledged paternity of John in the diaries, either referring to him as "Phibbah's child" or "Mulatto John". John was born in April of 1760 in a difficult birth, assisted by a midwife from Salt River estate called Old Daphne and House Franke, his mother's close friend and business partner. In the days following his birth, John was nursed by an Egypt fieldwoman named Egypt Lucy, who would go on to become one of his mother's closest friends, business partners, and a caregiver for John when his parents moved away from him. Phibbah secured a promise from Thistlewood in October of 1761 that John would be granted his freedom and in May of 1762, he fulfilled that promise. During the majority of his childhood, the freed John was sent to live in a boarding school for mixed race children where he learned how to read and write, was eventually apprenticed to become a carpenter at the age of 15, and allowed to join in Jamaica's 'colored' militia. One of his childhood friends was James, the son of a mixed race domestic laborer named Little Mimber on a neighboring plantation. John was not diligent in his apprenticeship, often absenting from work for days on end. He was frequently in debt, and involved in domestic disputes. John lived to the age of twenty, then died in September of 1780 of a sudden, putrid stomach infection that turned his fingernails black and shredded his intestines. Phibbah was beside herself with grief, later suspecting that he had been willfully poisoned as a result of a love triangle gone horribly wrong. The death struck a heavy blow to the broader enslaved community, many of whom came to his burial. John’s half-sister Accubah came to stay with their mother for several weeks afterwards.
A11: P10 | B11: HOUSE FRANKE | D11: ? | F11: PARADISE ESTATE | G11: L2 | H11: House Franke was an enslaved domestic laborer who lived on Paradise estate. She was a very close friend of Phibbah [the housekeeper of Egypt estate], Phibbah's sister Nancy, Phibbah's daughter Accubah [also known as Coobah and later, Jenny Young], an enslaved domestic laborer and healer named Vine, and an enslaved Egypt fieldwoman named Egypt Lucy. Together, the six women pooled the money and resources they earned through the selling of goods they raised from their provison grounds, their raising of livestock, and from sewing work they were contracted to perform for whites. They intended the funds to be used to purchase at least one of each other's freedom. House Franke had a husband named Paradise Jack who (presumably) lived with her at Paradise. House Franke was a very frequent visitor to Egypt, and to Breadnut Island Pen to visit with Phibbah. When Phibbah gave birth to John in 1760, House Franke came and stayed at Egypt for several days to assist at her bedside. When Phibbah herself fell ill, House Franke came and stayed with her again to nurse her back to health. Like Egypt Lucy, House Franke also mantained a significant presence in the lives of Phbbah's children (who did not live with her for the majority of the time). House Franke was a relatively prosperous businessowman and in 1769, she along with Phibbah, and Egypt Lucy gave Thistlewood a 27 pound loan to help him in his transition from Egypt's overseer to an independeny penkeeper of a property called Breadnut Island Pen. He would repay the loan about a year later. House Franke made a second loan to Thistlewood in December of 1770; he repaid it in September of 1771.
A12: P11 | B12: OLD DAPHNE | D12: ? | F12: SALT RIVER ESTATE | G12: L4 | H12: Old Daphne was an enslaved 'grannie' midwife who resided on Salt River Estate. She was called to preside over at least fivw different childbirths over the course of about a decade, including Phibbah, the housekeeper of Egypt estate and three enslaved fieldwomen named Jenny, Anjaw, Mountain Lucy and Sarah.
A13: P12 | B13: VINE | D13: MOST LIKELY AT LEAST HALF AFRICAN | F13: CABARITTA ESTATE | G13: L8 | H13: Vine was a full blooded African or a first generation Afro-Creole domestic laborer who lived on a neighboring plantation called Cabaritta Estate owned by one of Thistlewood's friends, Samuel Say. She was the daughter of at least one enslaved African parent, a man named Old Pompey who belonged to another of Thistlewood's friends named Jeremiah Meyer and lived on his estate of Meylersfield. When Vine's mother died in 1764, the enslaved community held a "play" (a communal funeral) in her honor. Vine was involved in various sexual/domestic partnerships over the course of several years, including one with a white man named MacArthur who was employed on the Roaring River estate, and another with a driver named Sam who lived on the property of a Mrs. Sarah Bennett (who would lster sell thistlewood Breadnut Island Pen). The diary never describes Vine as having any children of her own. However, she was a regular presence in the lives of her friends' children, especially that of her friend Phibbah [the housekeeper of Egypt Estate) and Phibbah's children John and Accubah, and Egypt Lucy's child Little Quashe. Vine was a very close friend of Phibbah, Phibbah's sister Nancy, an enslaved domestic woman from Paradise Estate named House Franke, and an enslaved field woman from Egypt Estate named Egypt Lucy. Vine, Phibbah and John were relatively privileged as domestic laborers, given leave by their masters to attend various social events througout the parish such as horse races. In a significant departure from most other enslaved people in Jamica who were forced to walk everywhere as their chief means of transportation, Vine owned her own horse named Powder Tail. Vine was a skilled healer and regularly attended to the sickbeds of enslaved men, women and children when they were ill--especially when they were friends or her friends' children. Vine was a skilled teller of Anansi spider stories, and frequently came to Egypt in the evenings to tell them to enslaved people and whites alike, sometimes alongside other enslaved Africans like Abba.
A14: P13 | B14: OGO | C14: MARIA | D14: EBO | E14: 4'11 INCHES HIGH (1761) 'TT' IN DOWNWARD TRIANGLE BRAND ON HER RIGHT SHOULDER (1761) | F14: EGYPT ESTATE (1761-1767) BREADNUT ISLAND PEN (1767-1786) | G14: L1; L3 | H14: Ogo first appeared in the diary in December of 1761. Thistlewood purchased her in a group sale of five other Africans from a trader for 50 pounds. Upon her arrival to Egypt estate, he paired her with an enslaved fieldwoman named Egypt Lucy to be 'seasoned'. After renaming her "Maria," a mere one week after her purchase, he put Ogo to work in Egypt's fields. Five years after her arrival in Jamaica, Ogo gave birth to her first child: a daughter named Lucy. Her father was most likely Solon, an enslaved field laborer and sometimes driver whom Thistlewood purchased a few months before Ogo. Over the next several years, Ogo would have several more sexual partners/spouses, including another enslaved man at the neighboring Retrieve estate, an enslaved man named Peter owned by another of Thistlewood's friends named Wilson, and an enslaved man from Egypt estate named Cubbena. Thistlewood forced himself upon her sexually several times. The diary also confirms Ogo as having two more children: a boy born in 1770 who died at seven days old of tetanus, and another daughter named Rachael born in 1771 who would die in 1775 at four years old. Her eldest daughter, Lucy would fall sick of stomach pains and convulsions and die in 1777 at the age of ten. In the years following her captivity, Ogo would act as a nurse/caregiver for Abasse (renamed Will) when he became seriously ill and died in 1767, who was one of the six that Thistlewood purchased in 1761 and was thus likely one of Ogo's shipmates. Ogo outlived Thistlewood by the time of his death in 1786. In a 1787 appraisal of his human property, she was estimated to be "about 40 years old) and valued at 50 pounds (the exact same price Thistlewood orginally paid for her in 1761).
A15: P14 | B15: LUCY | C15: LITTLE LUCY | D15: AFRICAN/AT LEAST HALF EBO | F15: PARADISE ESTATE (1766) EGYPT ESTATE (1766-1767) BREADNUT ISLAND PEN (1767-1777) | G15: L2; L1; L3 | H15: Little Lucy was born in November of 1766 to Ogo, an "Ebo" young woman and fieldhand and Solon, an African young man and fieldhand on Paradise Estate, both purcahsed by Thistlewood in 1761. Her mother was assisted in the delivery by an enslaved grannie named Paradise Quasheba. Little Lucy would have two siblings: a brother born in 1770 who died at just seven days old of tetanus, and a younger sister, Rachael, born in 1771 and and who would die in 1775 at four years old. Little Lucy was often sick, and subject to frequent injuries over her life, but she often was able to recover. In 1777, she became extremely ill of stomach and neck pains for several days before falling into convulsions and dying at the age of ten--a milestone in a time and place when most enslaved children died before reaching the age of two. Solon dug her grave. On the evening of her burial, a moon/lunar rainbow appeared in the sky.
A16: P15 | B16: NANNY | D16: AFRICAN | F16: KINGSTON EGYPT ESTATE BREADNUT ISLAND PEN | G16: L19; L1; L3 | H16: Nanny was an enslaved African young woman purchased by John Cope on Thistlewood's behalf in July of 1761 in Kingston, alongside two other African men: Solon and Caesar, who were also most likely her shipmates. She was presumed to be 21 years old. Nanny had just one daughter, born in August of 1766 "in the height of bad weather" at a neighboring estate called Paradise. Nanny was assisted in the birth by an enslaved grannie named Paradise Quasheba. Her daughter was named Little Phibbah. In the Spring of 1768, Nanny was entrusted with caring for Molia's (renaned Coobah) only child Silvia while Molia was hired out to labor on a neighboring plantation. Silvia fell sick while her mother was away and died at 15 months old. Little Phibbah was often ill througnout her life, and in 1771 she died at age of five after a long and painful bout of stomach worms. Nanny would be one of the enslaved people on Breadnut Island Pen who would go on to outlive Thistlewood following his death in 1786. In a 1787 appraisal of his human property she was estimated to be "about 47 years old" and valued at 60 pounds.
A17: P16 | B17: COOBAH | C17: ACCUBBAH; JENNY YOUNG; PHIBBAH'S COOBAH | D17: ? | F17: PARADISE ESTATE | G17: L2 | H17: Accubah, also known as 'Coobah' was an enslaved Afro-Creole girl born to Phibbah, the housekeeper of Egypt Estate and an unknown father sometime during the 1750s. Throughout her childhood, she mostly lived apart from her mother on Paradise, a neighboring sugar estate that was also owned by their owners John and Mary (Molly) Copeand served as a domestic servant to Molly Cope. Accubah was later sent to a school for mixed race children at an early age to learn to read and write. In addition to being frequently separated from her mother, Accubah was frequently the target of sexual predation from white men, including John Cope and a white laborer on Egypt named Sam Matthews who attempted to rape her in Egypt's boiling house in before being thwarted, ironically enough, by Thistlewood himself. She was one of the only enslaved girls/women in the diary who he never forced himself upon sexually. Accubah had a number of sexual partners over the years who were mostly either free mixed race men of color, or white men. Three of the mixed race men were described as being her 'husband': Mulatto Davie in 1761, Nagua in 1766 (who also appeared to have grown up with Accubah on the estate), and Jimmy Stewart in 1776. Accubah was an accomplished seamstress, who put her skills to good use in taking on paid sewing jobs for Thistlewood, and also sewing intricate messages into the dresses and bodices of her fellow enslaved women. At some point during the late 1760's Accubah became involved in the cult society of Myalism; an Afro-Jamaican religion that according to what some scholars have argued was “the first religious organization of Africans in Jamaica” that “addressed itself to the entire slave society." Myal was organized around the premise that enslaved people could inure themselves to the many dangers and predations from white Accubah was very close with her mother PhIbbah, and with her mother Phibbah's friends: Accubah's aunt Nancy, an enslaved domestic woman who also lived at Paradise named House Franke, an enslaved domestic woman and healer named Vine from Cabaritta estate and an enslaved field woman from Egypt named Egypt Lucy. Together, the six women pooled the money and resources they earned through the selling of goods they raised from their provison grounds, their raising of livestock, and from sewing work they were contracted to perform for whites. They intended the funds to be used to purchase at least one of each other's freedom. Accubah was very fond of hearing Anansi spider tales told by her mother's close friend, an enslaved healer from Cabarittta Estate named Vine. She made regular trips to her mother's later residence of Breadnut Island Pen to hear them under the cover of night. Accubah traveled abroad to England twice in her lifetime; once in 1767 and once in the spring of 1771, as a domestic to the Cope's two daughters. On her second trip, she was baptized into the Church of England and christened 'Jenny Young', a name she would go by for the rest of her life after returning to Jamaica. Accubah had seversl children over the course of her life, but only one of whom would survive into childhood: Little Nancy (presumably named after her Aunt). Like her mother, Accubah/Jenny Young would go onto outlive Thistlewood past his death in 1786, although it is unknown whether or not she would ever receive her freedom like her mother did.
A18: P17 | B18: SALLY | D18: CONGO | E18: 4'1 INCHES HIGH (1762) | F18: BREADNUT ISLAND PEN | G18: L3 | H18: Sally first appears in the diary in April of 1762 in a purchase that Thistlewood made from one his white associates/friends Jeremiah Meyler. He described her as a "Congo girl" of no more than "9 or 10 years old" and standing at just 4'1 inches tall. He paid 42 pounds cash for her. Sally was originally intended and trained to be a seamstress/domestic laborer, but for the next twenty two years, she would put up regular and varied shows of resistance to every job, assignment or position that Thistlewood tried to force upon her. Even after he eventually relegated her to his field gang, Sally regularly stole food and other possessions from both white and endlsved Black people throughout the neighborhood. Over the course of her twenty two years in Jamaica, she ran away at least twelve different times. Sally was the victim of many acts of sexual assault and terrorism from various white men. (including Thistlewood) that mutilated her genitals, which probably attributed to the fact that she never had any children, nor was confirmed as ever being pregnant. Like many field laborers in Jamaica, she was often ill from yaws (which resulted in the amputation of one of her toes), and from venereal diseases. In November of 1784, Thistlewood sold Sally to anther trader, who transported her off the island altogether and to an unknown location.
A19: P18 | B19: PARADISE QUASHEBA | D19: ? | F19: PARADISE ESTATE | G19: L2 | H19: Paradise Quasheba was an enslaved 'grannie' (midwife) who lived on Paradise Estate. She attended at least eleven different enslaved women's births between 1759-1766: Egypt Lucy, Nancy, Rosanna, Moll, Agnes, Jenny, Wonga, Molia, Ogo, Nanny and Eve--the majority of whose infants survived both a 9 day observing period and several years into their childhoods.
A20: P19 | B20: PEGGY | D20: AFRICAN | E20: 5'1 INCHES HIGH SCAR ON LEFT CHEEK BACK AND BELLY FULL OF COUNTRY MARKS HOLES THROUGH HER NOSE (1765) 'TT' BRAND ON HER RIGHT SHOULDER SCARS FROM REPEATED FLOGGINGS | F20: BREADNUT ISLAND PEN | G20: L3 | H20: Peggy was an African young woman who first appeared in the diary in 1765 when Thistlewood attended a 'slave scramble' aboard a Guinea ship and purchased her alongside 9 other enslaved Africans (5 young men and 4 other young women in total). These 9 Africans were Peggy's shipmates: Syphox, Cudjoe, Chub, Bristol, Jmmy, Myrtilla, Phoebe, Franke and Damsel). Thistlewood presumed her to be "about 16 or 17 years old." Peggy was assigned to field labor for the next twenty one years. She was often ill of yaws. Thistlewood also speculated that at times, she showed signs of being "disordered in her senses," although he doesn't specify why/how. If Peggy ever had a husband/domestic partner, Thistlewood never knew or recorded it. She never bore any children, nor was she ever described as ever being pregnant. For several years, she shared a household with her fellow field gang member Molia [Coobah] and Molia's daughter, Silvia. Follwing Silvia's death, Peggy continued to share a household with Molia until 1774 when Thistlewood, frustrated with her repeated escaps attempts, sold her to a trader who trafficked her to Georgia. Peggy was caught engaging in geophagia (eating dirt) in 1774 and was flogged for it (notably for the first time). An accident involving a driver and a whip caused her right eye to be severely mutilated in June of 1780. She was one of the enslaved community who outlived Thistlewood following his death in 1786. In a 1787 appraisal, she was estimated to be about 39 years old, described as "distempered," "blind in one eye" and valued at 10 pounds.
A21: P20 | B21: ABBA'S JOHNIE | D21: AT LEAST HALF AFRICAN | F21: EGYPT ESTATE BREADNUT ISLAND PEN | G21: L1; L3 | H21: Johnie was born in 1764 to Abba, an enslaved African domestic laborer that Thistlewood first purchased in 1758. His father may have been Neptune, an enslaved man belonging to a white man named Emotson, one of Thistlewood's friends who also owned a tavern in Savanna la Mar and was described as Abba's "husband" around the time of his birth. He had three surviving siblings who: an elder sister named Mary, a younger brother named Neptune and a younger sister named Jenny. Johnie lived to the age of seven (a milestone for a child in Jamaica at that time). In January of 1771, he became deathly ill, suffering from stmach cramps and falling into "faints"/"fits" (seizures). Vine, an enslaved domestic laborer and healer from the neighboring Cabaritta estate came to "bleed" and tend to Johnie. Three days later Thistlewood himself sent Abba with Johnie to the parish Bay to be seen and treated by a white physician, but Johnie died on the trip back home. Abba was inconsolable with grief. Johnie was buried that same evening near his mother's house. Numerous enslaved people from surrounding estates and pens, including Vine, attended his funeral, singing over him. Several months later in July 1771, Abba was still in mourning for Johnie, engaging in the practice of 'throwing water' and participating in communal songs and drumming in his honor.
A22: P21 | B22: ABBA'S MARY | D22: AT LEAST HALF AFRICAN | F22: BREADNUT ISLAND PEN | G22: L2 | H22: Mary was born in January 1762, the first daughter/child of Abba, an African young woman and Neptune, an enslaved man belonging to a white man named Emotson, one of Thistlewood's friends who also owned a tavern in Savanna la Mar. She had three surviving siblings: Johnie, Neptune, and Jenny. In March/April of 1763, Mary contracted smallpox; though she ultimately recovered from the disease itself, she was permanently blinded. The diary describes Mary as having one husband/domestic partner on a neighboring sugar estate called Three Mile River named Quacoo with whom she had two children: one daughter born in 1784 who died at 1 week old, aand another daughter born in 1785 named Prue who was still alive by the time of Thistlewood's death inn 1786. Like her mother, Mary outlived Thistlewood. Inan appraisal of the complete inventory of all his human property, her value was estimated to be just 1 pound.
A23: P22 | B23: LITTLE PHIBBAH | D23: AT LEAST HALF AFRICAN | F23: PARADISE ESTATE EGYPT ESTATE BREADNUT ISLAND PEN | G23: L2; L1; L3 | H23: Little Phibbah was born in August 1766 at Paradise Estate in "the height of bad weather" to an enslaved African woman named Nanny and an unknown father. A midwife named Paradise Quasheba was in attendance at her birth. Little Phibbah was frequently ill and cared for by her mother. When she was five years old, she became very badly afflicted with stomach worms. After being treated repeatedly by her mother, Thistlewood and white physicians over the course of several days, she died on September 9 1771. Two enslaved men named Lincoln and Abasse dug her grave and buried her the next evening.
A24: P23 | B24: SHIPMATE | D24: AFRICAN | F24: BLUEFIELDS BAY | G24: L11 | H24: In November of 1770, an enslaved "Ebo" woman named Molia made her seventh esacpe from Breadnut Island Pen. She stayed missing for eleven days before being caught at a place called Bluefields Bay and brought back to the Pen. At some point during this recovery Molia told someone that she had gone to Bluefields Bay for a specific purpose; this purpose was to see a person she desccribed as her "shipmate". This unnamed/unidentified person was Molia's shipmate with whom she had, presumably, survived hte Middle Passage voyage at least nearly a decade earlier and with whom she had maintained a close and intimate relationship. It is the first and on;y time that this Shipmate would ever be mentioned in the diary.
A25: P24 | B25: LINCOLN | D25: EBO | F25: EGYPT ESTATE BREADNUT ISLAND PEN | G25: L1; L3 | H25: Lincoln first appears in the diary in Janury of 1756 as the very first enslaved person Thistlewood purchased for 43 pounds. Presumed to be an "Ebo", he was described as being 16 years of age, and 4 ft 9 inches tall. Throughout the course of those three decades, Thistlewood regularly appointed him to skilled positions such as a fisherman and a driver of the field gangs. He regularly entrusted him with the use and possession of a gun with which to hunt game and also regularly sent him out to search for and retrieve the most troublesome of runaways. Lincoln was the most frequent recipient of Thistlewood’s castoff clothes and worn possessions that he no longer wanted. The rations of food and rum he received were markedly higher than nearly everyone else’s. Lincoln had multiple domestic and sexual relationships, including one with an Egypt field woman named Violet, another named Egypt Susanah, and another African domestic laborer owned by Thistlewood named Abba. Lincoln and Abba would have two children together: a daughter named Jenny born in August of 1772, and a daughter named Phibbah born in April of 1776. Lincoln's longest core relationship however, was with Sukey, an African young woman who Thistlewood purchased in 1761 from a trader named John Hutt; they never had any children. Many of Lincoln's relationships with women were fraught with tension, even to the point of domestic violence. Lincoln would be one of the enslaved population on Breadnut Island Pen who would go on to outlive Thistlewood past his death in 1786. Presumed to be 47 years old in a 2787 appraisal, his value was assessed at 50 pounds.
A26: P25 | B26: MASON QUASHE | D26: ? | H26: Mason Quashe was an enslaved man who belonged to Elizabeth Anderson, a "free coloured (mixed race) woman"who was the mistress of William Dorrill, Thistlewood's first empoyer and the initial owner of Egypt, Salt River and Paradise upon his arrival in Jamaica. She frequently hired Mason Quashe out to Egypt and other estates throughout the parish where he performed a wide array of skilled and very highly sought after labors such as masonry, carpentry, fishing, and driving of the field gangs. He was 'paid' for these labors in rum and castoff clothing from white men. Mason Quashe was a prominent figure in the enslaved community of Westmoreland, and held close relationships with other prominent figures in that community such as Phibbah, the housekeeper of Egypt, and the other women in her social circle such as House Franke and Egypt Lucy, who tended/cared for him in times of illness. Mason Quashe had a number of sexual/domestic relationships with several enslaved women throughout the neighborhood, including one with Egypt field woman Egypt Lucy, who left her previous husband Daniel for him--their union rrsulted in a son born in December of 1759: Little Quashe. He also had another child, a daughter named Franke who lived on a neighboring estate. Mason Quashe's status as a skilled laborer seemed to give him a relative amount of privilege, particularly in his abilty to move around the parish, and beyond it. In 1767, he traveled abroad to British North America, where he would pass away from complications of gout and stomach maladies in 1767.
A27: P26 | B27: SOLON | D27: AFRICAN | F27: BREADNUT ISLAND PEN | G27: L3 | H27: Solon first appears in the diaries in July of 1761 when he was acquired by John Cope on Thistlewood's behalf from a slave market in Kingston alongside two others: an African woman named Nanny and an African young man named Caesar. Thistlewood paid 50 pounds for each one of them. He also described Solon as being "about 16". In later years, Solon would (like many others) be taken ill with various ailments and diseases such as stomach cramps, guinea worms, eye infections, and yaws. Solon was a skilled fisherman and was often sent by Thistlewood to catch fish for him in nearby rivers and streaams. He was also frequently sent out to search for escaped runaways, particularly a young 'Ebo' woman named Molia who ran away from Thistlewood at least 14 times between 1769-1774. Solon was the domestic partner/'husband' of Ogo (renamed 'Maria'), a presumed 'Ebo' African young woman purchased by Thistlewood from a slave trader named John Hutt in December of 1761. They had at least one child together: a daughter named Lucy, b0rn in November of 1766, who lived to the age of ten before dying in 1777 from stomach ailments.
A28: P27 | B28: WANGA | C28: PRINCESS | D28: AFRICAN | F28: EGYPT ESTATE | G28: L1 | H28: Wanga was an African woman who was purchased and brought to Egypt to work as field laborer in May of 1754 shortly after Thistlewood's arrival in the early 1750's. Upon her purchase, she was renamed "Princess," and paired with another enslaved woman named Quashe who served as her 'seasoner'. Wanga would have several confirmed sexual/domestic partners over the course of the sixteen years that Thistlewood served as overseer at Egypt. Among them were a driver named Hazat, and an Ebo man and skilled laborer named Cyrus, with whom she had a son in January of 1757 named Little Dick. Although he survived his first two years of life, Little Dick was badly afflicted with yaws, a severe bacterial infection that resulted in skin lesions, joint inflammation and bone pain/deformities. In July of 1759, Little Dick passed away from the complications of yaws. Two months later his father, Cyrus, would go on to hold a "feast" (funeral ceremony) in his honor. In 1761, Wanga was assigned to be the seasoner of an estimated 15 year old 'Ebo' young woman named Molia who had been purchased by Thistlewood and who he renamed 'Coobah'. Wanga ran away from the estate once in the spring of 1762. She was also pregnant at the time of her escape. Daniel, a skilled laborer was sent to search for and return her to the estate. She was later sent to Paradise estate to lie-in and give birth to a daughter named Charlotte, who survived at least until her second year.
A29: P28 | B29: OLD LEANDRA | D29: AFRICAN | F29: MRS. BENNETTS | H29: Old Leandra was an enslaved African woman and 'grannie' (midwife) who belonged to Sarah Bennett, a wealthy white proprietress who would later go on to sell Thistlewood Breadnut Island Pen in 1767. As a young(er) woman and captive upon a Middle Passage slave ship sailing from Guinea, Old Leandra was sexually coerced by the captain of the ship. She was alleged to have betrayed a plot of a shipboard rebellion to him in exchange for her freedom. Upon reaching Jamaica, the Captain temporarily left her in the keeping of a proprietor called Cunningham, supposedly as a "free person," until his return to reclaim her; he died while away. Neither Cunningham nor his son honored the agreement to give Old Leandra her freedom, and eventually sold her to Sarah Bennett, with whom she remained for many years. It would not be until 1772 when Old Leandra was an elderly woman and (presumably) of little to no further use to Sarah Bennett that Bennett abruptly announced to Old Leandra that she was at last free "to go where she pleases." The diary does not give a clear indication of where she lived following this 'release', but Old Leandra would go on to serve as a nurse and birthing attendant for Abba and Molia, two other women enslaved by Thistlewood. Old Leandra was a caregiver for enslaved children, most particularly for [Mulatto] John, the mixed race son of Thistlewood and Egypt's housekeeper Phibbah who lived with Sarah Bennett while attending a school for mixed race children.
A30: P29 | B30: JOB | D30: ? | F30: EGYPT ESTATE | G30: L1
A31: P30 | B31: MOUNTAIN LUCY | D31: ? | F31: EGYPT ESTATE | G31: L1 | H31: Mountain Lucy was an enslaved fieldwoman who lived and worked on Egypt estate from as early as 1754. Like many other fieldhands, Mountain Lucy lived in conditions of immense poverty and food scarcity. Throughout periods of particularly severe famine and droughts on the estate, she appeared to have engaged in a coercive sexual relationship with Thistlewood in exchange for food, "bitts" (money), and other presents. In 1755, when Egypt's domestic housekeeper Phibbah became pregnant, she "brought" Mountain Lucy to Thistlewood to "keep" as a "sweetheart" (sexual partner) while she was in her latter trimester of pregnancy. Thistlewood initially resisted the arrangement, but eventually relented. Mountain Lucy was the mother of at least four children. In 1756, she gave birth to a girl, Prue, who managed to survive at least until the age of 8 (an enormous milestone for enslaved chilren in Jamaica), and who Mountain Lucy claimed had been fathered by Thistlewood, presumably duringPhibbah';s lying in period (although he denied this). Between 1758 and 1759, she gave birth to two boys, once each year, who both died within days. Another girl, Flora would follow in 1761 and survive until at least the age of 3. Mountain Lucy ran away from the estate at least twice in 1756. She was found within days on both occasions and punished with brutal floggings and gaggings. She was also punished on multiple occasions for giving verbal protests to the drivers in the field
A32: P31 | B32: FANNY | D32: ?
A33: P32 | B33: MIRTILLA | C33: MYRTILLA | D33: SOCO | E33: TWO BLACK MARKS DESCENDING OBLIQUELY FROM HER EYES AND HER BELLY FULL OF COUNTRY MARKS | F33: EGYPT ESTATE | G33: L1
A34: P33 | B34: ELLIN | D34: EBO | F34: EGYPT ESTATE | G34: L1
A35: P34 | B35: DAMSEL | D35: CHAMBOY | E35: 4'8 INCHES HIGH ON HER FACE, 3 LONG STROKES DOWN EACH CHEEK, 2 SMALL OBLIQUE, ETC. HER BELLY FULL OF COUNTRY MARKS & AN IN ARCH BETWEEN HER BREASTS. (1765) | F35: BREADNUT ISLAND PEN | G35: L3
A36: P35 | B36: PARADISE JACK | D36: ? | F36: PARADISE ESTATE | G36: L2
A37: P36 | B37: OLD POMPEY | D37: MOST LIKELY AFRICAN
A38: P37 | B38: SUKEY | D38: AFRICAN | E38: 4'8 HIGH (1761) 'TT' IN DOWNWARD TRIANGLE BRAND ON HER RIGHT SHOULDER (1761) | F38: EGYPT ESTATE BREADNUT ISLAND PEN | G38: L1; L3
A39: P38 | B39: SAWNO; DOWOTRONNY | C39: DICK | D39: AFRICAN | E39: 5'7 HIGH (1761) "TT" IN DOWNWARD TRIANGLE BRAND ON HIS RIGHT SHOULDER | F39: EGYPT ESTATE BREADNUT ISLAND PEN | G39: L1; L3
A40: P39 | B40: ABASSE | C40: WILL | D40: EBO | E40: 5'3 HIGH (1761) "TT" IN DOWNWARD TRIANGLE BRAND ON HIS RIGHT SHOULDER | F40: EGYPT ESTATE BREADNUT ISLAND PEN | G40: L1; L3
A41: P40 | B41: OWORIA | C41: POMPEY | D41: COROMANTEE | E41: 4'9 HIGH (1761) 'TT' IN DOWNWARD TRIANGLE BRAND ON HIS RIGHT SHOULDER (1761) | F41: EGYPT ESTATE BREADNUT ISLAND PEN | G41: L1; L3
A42: P41 | B42: BESS | D42: ? | F42: BREADNUT ISLAND PEN | G42: L3
A43: P42 | B43: DANIEL | D43: ? | F43: EGYPT ESTATE | G43: L1
A44: P43 | B44: THE OVERSEER | C44: THOMAS THISTLEWOOD NO FOR PLAY | D44: ENGLISH/BRITISH | F44: VINEYARD PEN EGYPT ESTATE BREADNUT ISLAND PEN | G44: L20; L1; L3
A45: P44 | B45: THE PLANTER | C45: JOHN COPE | D45: ENGLISH/BRITISH | F45: PARADISE ESTATE EGYPT ESTATE | G45: L2; L1
A46: P45 | B46: THE PLANTER'S WIFE | C46: MARY (MOLLY) COPE | D46: ENGLISH/BRITISH | F46: PARADISE ESTATE EGYPT ESTATE | G46: L2; L1
A47: P46 | B47: THE NEIGHBOR | C47: SAMUEL SAY | D47: ENGLISH/BRITISH | F47: CABARITTA ESTATE | G47: L8
A48: P47 | B48: THE CAPTAIN | C48: ARTHUR FOREST | D48: ENGLISH/BRITISH | F48: MASEMURE ESTATE | G48: L6
A49: P48 | C49: DAVID KINLOCK | D49: ENGLISH/BRITISH | F49: MASEMURE ESTATE | G49: L6
A50: P49 | C50: GEORGE LESLEY | D50: ENGLISH/BRITISH
A51: P50 | B51: THE PROPRIETRESS | C51: SARAH BENNETT | D51: ENGLISH/BRITISH | F51: SARAH BENNETT'S | G51: L18
A52: P51 | B52: THE SLAVE TRADER | C52: JOHN HUTT | D52: ENGLISH/BRITISH
A53: P52 | B53: CUDJOE | D53: ?
A54: P53 | C54: JAMES LYMBORNER | D54: ENGLISH/BRITISH | F54: PARADISE ESTATE | G54: L2
A55: P54 | B55: JIMMY | D55: COROMANTEE OR SHANTE | E55: 4'5 INCHES HIGH (1765) 'TT' IN DOWNWARD TRIANGLE BRAND ON HIS RIGHT SHOULDER
A56: P55 | B56: THE OVERSEER'S NEPHEW | C56: JOHN THISTLEWOOD | D56: ENGLISH/BRITISH | F56: EGYPT ESTATE | G56: L1
A57: P56 | B57: LITTLE NANCY | D57: ? | F57: PARADISE ESTATE | G57: L2
A58: P57 | B58: CHUB | D58: AFRICAN | E58: 4'10 HIGH 3 PERPINDICULAR SCARS DOWN EACH CHEEK 'TT' IN DOWNWARD TRIANGLE BRAND ON HIS RIGHT SHOULDER (1765)
A59: P58 | B59: PHOEBE | D59: COROMANTEE | E59: 4'7 INCHES HIGH VERY BLACK EYEBROWS 'TT' IN DOWNWARD TRIANGLE BRAND ON HER RIGHT SHOULDER(1765) | F59: BREADNUT ISLAND PEN
A60: P59 | B60: FRANKE | D60: AFRICAN | E60: 4'9 INCHES HIGH, HER FACE ALL OVER CHAMPHERRED 'TT' IN DOWNWARD TRIANGLE BRAND ON HER RIGHT SHOULDER (1765) | F60: BREADNUT ISLAND PEN
A61: P60 | B61: CUDJOE | D61: COROMANTEE | E61: 5'6 INCHES HIGH 3 SPONTS ON HIS RIGHT CHEEK, 4 ON HIS LEFT 'TT' IN DOWNWARD TRIANGLE BRAND ON HIS RIGHT SHOULDER (1765) | F61: BREADNUT ISLAND PEN
A62: P61 | B62: OLD CUDJOE | D62: ?
A63: P62 | B63: SYPHOX | D63: TEMNE DONCO | E63: 5'5 INCHES HIGH SEVERAL ROWS OF PUNCTURES ACROSS THE BELLY & THUS ON FACE 'TT' IN DOWNWARD TRIANGLE BRAND ON HIS RIGHT SHOULDER (1765)
A64: P63 | B64: BRISTOL | D64: SOCO | E64: 5'1 INCHES HIGH SEVERAL PERPINDICULAR SMALL & ONE DIAGONAL SCAR ON EACH CHEEK 'TT' IN DOWNWARD TRIANGLE BRAND ON HER RIGHT SHOULDER (1765)
A65: P64 | C65: JOHN STONE | D65: BRITISH/ENGLISH
A66: P66 | C66: DR. DRUMMOND | D66: BRITISH/ENGLISH
A67: P67 | C67: RICHARD CROTCHER | D67: BRITISH/ENGLISH
A68: P68 | C68: CHARLES GRAHAM | D68: BRITISH/ENGLISH
A69: P69 | C69: MR. PARKER | D69: BRITISH/ENGLISH
A70: P70 | B70: THE LAWYER | C70: MR. CHAMBERS | D70: BRITISH/ENGLISH
A71: P71 | B71: STROP | D71: ?
A72: P72 | C72: MR. BEAN | D72: BRITISH/ENGLISH
A73: P73 | B73: WANICKER | D73: AFRICAN | F73: SALT RIVER ESTATE | G73: L4
A74: P74 | B74: OLD SHARPER | D74: MOST LIKELY AFRICAN
A75: P75 | C75: WILLIAM DORRILL | D75: BRITISH/ENGLISH | F75: SALT RIVER ESTATE | G75: L4
A76: P76 | B76: ELIZABETH ANDERSON | D76: MIXED RACE (OCTROON) | E76: FAIR SKIN (MIXED RACE) | F76: SALT RIVER ESTATE | G76: L4
A77: P77 | B77: NACOMMA | C77: CYNTHIA | D77: BAMBARAH, CRIPPAH OR TINNEDONE | F77: SALT RIVER ESTATE | G77: L4
A78: P78 | B78: COLONEL CUDJOE (MAROON) | D78: ?
A79: P79 | C79: (SAM)UEL MATHEWS | D79: ENGLISH/BRITISH
A80: P80 | B80: LITTLE MIMBER | D80: ?
A81: P81 | C81: JOHN HARTNOLE | D81: ENGLISH/BRITISH
A82: P82 | B82: HAGAR | D82: ? | F82: EGYPT ESTATE | G82: L1
A83: P83 | C83: JOHN PARKINSON | D83: ENGLISH/BRITISH
A84: P84 | B84: JOHNIE [MALE DRIVER] | D84: AFRICAN | F84: EGYPT ESTATE | G84: L1
A85: P85 | B85: SIMON | D85: AFRICAN | F85: EGYPT ESTATE | G85: L1
A86: P86 | B86: CUFFEE | D86: ? | F86: EGYPT ESTATE | G86: L1
A87: P87 | B87: HAZAT | D87: ? | F87: EGYPT ESTATE | G87: L1
A88: P88 | B88: TOM | D88: ?
A89: P89 | B89: BACCHUS | D89: ?
A90: P90 | B90: MR. MOULD'S NANCY | D90: ?
A91: P91 | B91: FLORA | D91: ?
A92: P92 | C92: MR. EMOTSON | D92: ENGLISH/BRITISH | F92: EMOTSON'S TAVERN
A93: P93 | C93: MRS. EMOTSON | D93: ENGLISH/BRITISH | F93: EMOTSON'S TAVERN
A94: P94 | C94: JACK COPE | D94: JAMAICAN CREOLE/ENGLISH
A95: P95 | C95: DR. JAMES WEDDERBURN | D95: ENGLISH/BRITISH
A96: P96 | B96: OLD PHIBBAH | D96: ?
A97: P97 | B97: EGYPT MIRTILLA | D97: ? | F97: EGYPT ESTATE | G97: L1
A98: P98 | B98: L. POMPEY | D98: ?
A99: P99 | B99: MR. HAYWARD'S SALLY | D99: ?
A100: P100 | B100: LITTLE FANNY | D100: ? | F100: BREADNUT ISLAND PEN | G100: L3
...

Sheet EVENTS
A1: EVENT ID | B1: ARCHIVE ID(S) | C1: DATE(S) | D1: EVENT DESCRIPTION | E1: PERSON IDS | F1: NAMES | G1: PERSON IDS | H1: NAMES/PERSON IDS | I1: EVENT TYPE | J1: ALTERNATE NAMES | K1: LOCATION | L1: LOCATION ID | M1: VLOOKUP | N1: TIME OF DAY (AM/PM) | O1: WEATHER | P1: SPECIAL SKILL
A2: E34 | B2: IMG 150, P.294-295 | C2: May 2, 1750 | D2: "I think Port Royal has somewhat a grander look in the streets than Kingston" | E2: THE OVERSEER (P43) | F2: THE OVERSEER | G2: P43 | H2: =CONCATENATE(F2," (",G2,")") -> THE OVERSEER (P43) | I2: GEOGRAPHY/TERRAIN | J2: THOMAS THISTLEWOOD | K2: PORT ROYAL | L2: L25 | M2: =VLOOKUP(L2, GLOSSARY!$A:$C, 2, FALSE) -> PORT ROYAL | N2: AM
A3: E35 | B3: IMG 152, P.298-299 | C3: May 11, 1750 | D3: "Mr. Dorrill's house is pleasantly situated about 1/4 off [sic] a mile from the sea and about 2 1/2 or 3 mile from Savanna la Mar, to the east, paved with wood, backed with stone or more properly lined has port holes for deffence [sic]. Wood columns on East side near Salt River." | E3: THE OVERSEER (P43) | F3: THE OVERSEER | G3: P43 | H3: =CONCATENATE(F3," (",G3,")") -> THE OVERSEER (P43) | I3: GEOGRAPHY/TERRAIN | J3: THOMAS THISTLEWOOD | K3: SALT RIVER ESTATE | L3: L4 | M3: =VLOOKUP(L3, GLOSSARY!$A:$C, 2, FALSE) -> SALT RIVER ESTATE | N3: AM
A4: E36 | B4: IMG 152, P.298-299 | C4: May 15, 1750 | D4: "Many runaway Negroes took up, Mr. Dorrill had his own whipp'd severely and rubb'd with pepper, salt, and lime juice." | E4: WILLIAM DORRILL (P75) | F4: WILLIAM DORRILL | G4: P75 | H4: =CONCATENATE(F4," (",G4,")") -> WILLIAM DORRILL (P75) | I4: PUNISHMENT/VIOLENCE | K4: SALT RIVER ESTATE | L4: L4 | M4: =VLOOKUP(L4, GLOSSARY!$A:$C, 2, FALSE) -> SALT RIVER ESTATE
A5: E37 | B5: IMG 152, P.298-299 | C5: May 15, 1750 | D5: "20 acres planted with logwood seed, and well minded, in 20 years time or less, would be a pretty fortune for a man." | H5: =CONCATENATE(F5," (",G5,")") -> () | I5: GARDENING/AGRICULTURE | K5: SALT RIVER ESTATE | L5: L4 | M5: =VLOOKUP(L5, GLOSSARY!$A:$C, 2, FALSE) -> SALT RIVER ESTATE
A6: E41 | B6: IMG 153, P.300-301 | C6: May 18, 1750 | D6: "Yesterday a runaway Negroe being dead and buried while we were away. Mr. Dorrill caused him to be took up, his head stuck upon a pole and his body burnt." | E6: WILLIAM DORRILL (P75) | F6: WILLIAM DORRILL | G6: P75 | H6: =CONCATENATE(F6," (",G6,")") -> WILLIAM DORRILL (P75) | I6: PUNISHMENT/VIOLENCE | K6: SALT RIVER ESTATE | L6: L4 | M6: =VLOOKUP(L6, GLOSSARY!$A:$C, 2, FALSE) -> SALT RIVER ESTATE | N6: AM
A7: E44 | B7: IMG 153, P.300-301 | C7: May 18, 1750 | D7: "surveyors ought to avoid pitching their forts near old trees, which frequently fall and make great havoc. Many deep and frightful cockpitts in the mountains." | E7: THE OVERSEER (P43) | F7: THE OVERSEER | G7: P43 | H7: =CONCATENATE(F7," (",G7,")") -> THE OVERSEER (P43) | I7: GEOGRAPHY/TERRAIN | K7: WILDERNESS | L7: L15 | M7: =VLOOKUP(L7, GLOSSARY!$A:$C, 2, FALSE) -> WILDERNESS | N7: AM
A8: E40 | B8: IMG 154, P.302-303 | C8: May 24, 1750 | D8: "All day running off lines in the Black Morass to adjust hte bounds off Mr. Bernard Senior's lands, saw a very large yellow snake speckled upon the back! Several Black snakes and a very ugly large toad upon the back of a tree about 4 foot from the ground." | E8: THE OVERSEER (P43) | F8: THE OVERSEER | G8: P43 | H8: =CONCATENATE(F8," (",G8,")") -> THE OVERSEER (P43) | I8: HUSBANDRY/LIVESTOCK/FISHING | J8: THOMAS THISTLEWOOD | K8: SALT RIVER ESTATE | L8: L4 | M8: =VLOOKUP(L8, GLOSSARY!$A:$C, 2, FALSE) -> SALT RIVER ESTATE | N8: AM
A9: E32 | B9: IMG 155, P.304-305 | C9: May 30, 1750 | D9: "Killed a large Black snake." | E9: THE OVERSEER (P43) | F9: THE OVERSEER | G9: P43 | H9: =CONCATENATE(F9," (",G9,")") -> THE OVERSEER (P43) | I9: HUSBANDRY/LIVESTOCK/FISHING | J9: THOMAS THISTLEWOOD | K9: VINEYARD PEN | L9: L20 | M9: =VLOOKUP(L9, GLOSSARY!$A:$C, 2, FALSE) -> VINEYARD PEN
A10: E33 | B10: IMG 155, P.304-305 | C10: May 31, 1750 | D10: "Killed a very large Black snake." | E10: THE OVERSEER (P43) | F10: THE OVERSEER | G10: P43 | H10: =CONCATENATE(F10," (",G10,")") -> THE OVERSEER (P43) | I10: HUSBANDRY/LIVESTOCK/FISHING | J10: THOMAS THISTLEWOOD | K10: VINEYARD PEN | L10: L20 | M10: =VLOOKUP(L10, GLOSSARY!$A:$C, 2, FALSE) -> VINEYARD PEN
A11: E33 | B11: IMG 155, P.304-305 | C11: May 31, 1750 | D11: "Slept last night in a hamack [sick] in a hutt on Mr, Dorrill's plantation walk...Old Sharper (Mrs Elizabeth Anderson's Negroe) a clever old fellow looks after it." | E11: THE OVERSEER (P43) | F11: THE OVERSEER OLD SHARPER | G11: P43 | H11: =CONCATENATE(F11," (",G11,")") -> THE OVERSEER OLD SHARPER (P43) | I11: MISCELLANEOUS | J11: THOMAS THISTLEWOOD | K11: SALT RIVER ESTATE | L11: L4 | M11: =VLOOKUP(L11, GLOSSARY!$A:$C, 2, FALSE) -> SALT RIVER ESTATE | N11: PM
A12: E42 | B12: IMG 155, P.304-305 | C12: June 1, 1750 | D12: "Between 8 and 9 miles from Dean's Valley, met Colonel Cudjew [sic], one of his wives, one of his sons, a Lieutenant, and other attendants. He shook me by the hand, and Begg'd a dram of us which we gave him. He had on a feathered hat, sword by his side, gun upon his shoulder & barefoot and Bare legged. Somewhat a majestic look. He brought to my memory the picture of Robinson Crusoe." | E12: COLONEL CUDJOE (P78) THE OVERSEER (P43) | F12: COLONEL CUDJOE THE OVERSEER | G12: P78 P43 | H12: =CONCATENATE(F12," (",G12,")") -> COLONEL CUDJOE THE OVERSEER (P78 P43) | I12: MAROONS/MARRONAGE | K12: WILDERNESS | L12: L15 | M12: =VLOOKUP(L12, GLOSSARY!$A:$C, 2, FALSE) -> WILDERNESS | N12: AM
A13: E43 | B13: IMG 155, P.304-305 | C13: June 1, 1750 | D13: "We got to Great River about 2 in the afternoon, which is a little above 11 1/4 miles from Dean's Valley. Great River is about 40 yards wide at the wath and 30 in other place. I bath'd in it. Here are the largest, finest limes I ever saw." | E13: THE OVERSEER (P43) | F13: THE OVERSEER | G13: P43 | H13: =CONCATENATE(F13," (",G13,")") -> THE OVERSEER (P43) | I13: GARDENING/AGRICULTURE | K13: WILDERNESS | L13: L15 | M13: =VLOOKUP(L13, GLOSSARY!$A:$C, 2, FALSE) -> WILDERNESS | N13: AM
A14: E43 | B14: IMG 155, P.304-305 | C14: June 1, 1750 | D14: "Din'd at Barracks, catt leapt up to catch swallows, saw many unknown trees, forests, etc...Reached the plantane walk before night, where are lay again, eat some clocking in Broth and pepper pott with Old Sharper, who is a sensible NEgroe and also some Tumtum of plantanes and fish beat together." | E14: THE OVERSEER (P43) OLD SHARPER (P74) | F14: THE OVERSEER OLD SHARPER | G14: P43 P74 | H14: =CONCATENATE(F14," (",G14,")") -> THE OVERSEER OLD SHARPER (P43 P74) | I14: GARDENING/AGRICULTURE | K14: WILDERNESS | L14: L15 | M14: =VLOOKUP(L14, GLOSSARY!$A:$C, 2, FALSE) -> WILDERNESS | N14: AM/PM
A15: E39 | B15: IMG 156, P.306-307 | C15: June 2, 1750 | D15: "At 4PM the smartest clap of thunder heard for many years, nor 2 pulsations after the lightning, I having at that time my finger upon my pulse.:" | E15: THE OVERSEER (P43) | F15: THE OVERSEER | G15: P43 | H15: =CONCATENATE(F15," (",G15,")") -> THE OVERSEER (P43) | I15: WEATHER | J15: THOMAS THISTLEWOOD | K15: SALT RIVER ESTATE | L15: L20 | M15: =VLOOKUP(L15, GLOSSARY!$A:$C, 2, FALSE) -> VINEYARD PEN | N15: PM
A16: E31 | B16: IMG230, P.391-392 | C16: October 2, 1750 | D16: "Saw a Negroe fellow nam'd English belonging to Fellerswood tried, cast, and hang's upon the 1st tree immediately for drawing his knife upon a white man, his hand cutt off, Body left unbury'd." | H16: =CONCATENATE(F16," (",G16,")") -> () | I16: PUNISHMENT/VIOLENCE | K16: VINEYARD PEN | L16: L20 | M16: =VLOOKUP(L16, GLOSSARY!$A:$C, 2, FALSE) -> VINEYARD PEN | N16: AM
A17: E30 | B17: IMG 238, P.401-402 | C17: October 31, 1750 | D17: "Wanicker says, in the ship she was brought over in it was agreed to rise, but they were discovered first. The pickaninnys brought the men that were confined knives, muskets & other weapons." | E17: WANICKER (P73) | F17: WANICKER | G17: P73 | H17: =CONCATENATE(F17," (",G17,")") -> WANICKER (P73) | I17: REBELLION/UPRISING | K17: VINEYARD PEN | L17: L20 | M17: =VLOOKUP(L17, GLOSSARY!$A:$C, 2, FALSE) -> VINEYARD PEN
A18: E46 | B18: IMG 258, P.531-532 | C18: December 25, 1750 | D18: "At night had Creolian, Congo and Coromantian etc Musick & dancing enough. Egg cordial plenty." | E18: THE OVERSEER (P43) | F18: THE OVERSEER | G18: P73 | H18: =CONCATENATE(F18," (",G18,")") -> THE OVERSEER (P73) | I18: RECREATION | K18: SALT RIVER ESTATE | L18: L4 | M18: =VLOOKUP(L18, GLOSSARY!$A:$C, 2, FALSE) -> SALT RIVER ESTATE | N18: PM
A19: E375 | B19: IMG 5, P.6-7 | C19: January 8, 1751 | D19: "Mr. Barton's story of a Barbadoes woman that was rap'd by three of them (at Kingston) in a short spruce, he the middle man yet she laid up bastard child to him and how he madde her explain himself." | F19: MR. BARTON BARBADOS WOMAN | G19: P305 P306 | H19: =CONCATENATE(F19,"(",G19,")") -> MR. BARTON BARBADOS WOMAN(P305 P306) | I19: PUNISHMENT/VIOLENCE | L19: L20 | M19: =VLOOKUP(L19, GLOSSARY!$A:$C, 2, FALSE) -> VINEYARD PEN | N19: AM
A20: E376 | B20: IMG 8, P.12-15 | C20: January 21, 1751 | D20: "Alligators in the night make a noise catchign mosquitos etc with their mouths, like clapping their hands pretty much." | H20: =CONCATENATE(F20,"(",G20,")") -> () | I20: MISCELLANEOUS | L20: L20 | M20: =VLOOKUP(L20, GLOSSARY!$A:$C, 2, FALSE) -> VINEYARD PEN | N20: PM
A21: E378 | B21: IMG 10, P.16-17 | C21: January 28, 1751 | D21: "Negroes, etc believe if you hurt a carrion crow or her eggs...that you will never be well, thill they be well, spoil'd or dead. Another piece of superstition amongst them, is that they imagine glass bottles and images they cutt in wood, etc, can tell them, who thieves anyting out of the ground where they are sett up, or stuck. *some throw dry rotten wood upon water to drop shatt (?), some make the water thick with cow dung, others dtop into (?) but out upon the water is best. Barton's Dick Negroes say, the powder of ratt stones dried and sprinkled upon anything and given to women you want, forces her to desire you." | F21: BARTON'S DICK | G21: P308 | H21: =CONCATENATE(F21,"(",G21,")") -> BARTON'S DICK(P308) | I21: SUPERSTITION | L21: L20 | M21: =VLOOKUP(L21, GLOSSARY!$A:$C, 2, FALSE) -> VINEYARD PEN | N21: AM
A22: E377 | B22: IMG 12, P.20-21 | C22: February 4, 1751 | D22: "Beneba gone to wash in the sea." | F22: BENEBA | G22: P307 | H22: =CONCATENATE(F22,"(",G22,")") -> BENEBA(P307) | I22: RECREATION | L22: L53 | M22: =VLOOKUP(L22, GLOSSARY!$A:$C, 2, FALSE) -> THE SEA | N22: AM
A23: E38 | B23: IMG 35, P.60A-61A | C23: April 18, 1751 | D23: "About 12 at night cum Cynthia alias Nacomma sup lect Matt in supio domo parlor. * She is a Bambarah Negroes call Crippah or Tinnedones, being brought into their country young." | E23: NACOMMA (P77) THE OVERSEER (P43) | F23: NACOMMA THE OVERSEER | G23: P77 P43 | H23: =CONCATENATE(F23," (",G23,")") -> NACOMMA THE OVERSEER (P77 P43) | I23: SEX | K23: SALT RIVER ESTATE | L23: L20 | M23: =VLOOKUP(L23, GLOSSARY!$A:$C, 2, FALSE) -> VINEYARD PEN | N23: PM
A24: E379 | B24: IMG 53, P.90-91 | C24: June 1, 1751 | D24: "Negroes won't sweep this house at night, however dirty, for say they, it will occasion them to have ill luck." | H24: =CONCATENATE(F24,"(",G24,")") -> () | I24: SUPERSTITION | L24: L20 | M24: =VLOOKUP(L24, GLOSSARY!$A:$C, 2, FALSE) -> VINEYARD PEN | N24: PM
A25: E380 | B25: IMG 54, P.92-93 | C25: June 5, 1751 | D25: "In the afternoon, Phibbah and Scipio go out wiht cloath, gave Phibbah a tickett that she may not be molested, thus: Vineyard Penn June 5, 1751 The bearer herself (a Negroe man and woman nam'd Scipio and Phbbah) in company, belong to the The Vineyard Penn and the property of Florentius Vassall, Esq by whose orders they go out wiht cloath to sell which is certigied by me, Thomas Thistlewood." | F25: VINEYARD PHIBBAH SCIPIO | G25: P309 P310 | H25: =CONCATENATE(F25,"(",G25,")") -> VINEYARD PHIBBAH SCIPIO(P309 P310) | I25: HIGGLING/PROVISION | L25: L12 | M25: =VLOOKUP(L25, GLOSSARY!$A:$C, 2, FALSE) -> THE ROAD(S) | N25: AM
A26: E380 | B26: IMG 55, P.94-95 | C26: June 7, 1751 | D26: "Hugo sick, Phibbah and Scipio out with cloath." | F26: HUGO VINEYARD PHIBBAH SCIPIO | G26: P309 P310 P311 | H26: =CONCATENATE(F26,"(",G26,")") -> HUGO VINEYARD PHIBBAH SCIPIO(P309 P310 P311) | I26: HIGGLING/PROVISION | L26: L12 | M26: =VLOOKUP(L26, GLOSSARY!$A:$C, 2, FALSE) -> THE ROAD(S)
A27: E380 | B27: IMG 55, P.94-95 | C27: June 8, 1751 | D27: "Dago sick, Betty at home as before. Rest. of Negroes employ'd as before. Phibbah and Scipio yet out with cloath | F27: DAGO BETTY VINEYARD PHIBBAH SCIPIO | G27: P121 P134 P309 P310 | H27: =CONCATENATE(F27,"(",G27,")") -> DAGO BETTY VINEYARD PHIBBAH SCIPIO(P121 P134 P309 P310) | I27: HIGGLING/PROVISION | L27: L12 | M27: =VLOOKUP(L27, GLOSSARY!$A:$C, 2, FALSE) -> THE ROAD(S) | N27: AM
A28: E381 | B28: IMG 55, P.94-95 | C28: June 9, 1751 | D28: "When mud walls are sufficiently dry adn very much crack'd in this country, they mix water, soft cow dung, and wood ashes with a dmall quanity of fine mould till it be pretty thick so as sccace as to run out of the hand. With this, they rub the walls ince or twice over and it will fill and cover all the cracks, etc." | H28: =CONCATENATE(F28,"(",G28,")") -> () | I28: MISCELLANEOUS | L28: l20 | M28: =VLOOKUP(L28, GLOSSARY!$A:$C, 2, FALSE) -> VINEYARD PEN | N28: am
A29: E380 | B29: IMG 56, P.96-97 | C29: June 10, 1751 | D29: "Phibbah and Scipio yet out." | F29: VINEYARD PHIBBAH SCIPIO | G29: P309 P310 | H29: =CONCATENATE(F29,"(",G29,")") -> VINEYARD PHIBBAH SCIPIO(P309 P310) | I29: HIGGLING/PROVISION | L29: L12 | M29: =VLOOKUP(L29, GLOSSARY!$A:$C, 2, FALSE) -> THE ROAD(S) | N29: AM
A30: E380 | B30: IMG 57, P.98-99 | C30: June 11, 1751 | D30: "Phibbah and Scipio returned from selling of cloath." | F30: VINEYARD PHIBBAH SCIPIO | G30: P309 P310 | H30: =CONCATENATE(F30,"(",G30,")") -> VINEYARD PHIBBAH SCIPIO(P309 P310) | I30: HIGGLING/PROVISION | L30: L20 | M30: =VLOOKUP(L30, GLOSSARY!$A:$C, 2, FALSE) -> VINEYARD PEN | N30: AM
A31: E382 | B31: img 71, p.124-125 | C31: June 25, 1751 | D31: "Sir Hans Sloane was nothing thought of in this country, accounted a mere old woman." | F31: HANS SLOANE | G31: P312 | H31: =CONCATENATE(F31,"(",G31,")") -> HANS SLOANE(P312) | I31: MISCELLANEOUS | L31: L20 | M31: =VLOOKUP(L31, GLOSSARY!$A:$C, 2, FALSE) -> VINEYARD PEN | N31: AM
A32: E383 | B32: IMG 74, P.130-131 | C32: June 26, 1751 | D32: "Dick's doggs names are the following: 'Gainst me, Fair to My Face, Help Myself, Creole Woman, Good Women's (?), Womens Want All, etc." | F32: VINEYARD DICK | G32: P314 | H32: =CONCATENATE(F32,"(",G32,")") -> VINEYARD DICK(P314) | I32: MISCELLANEOUS | L32: L20 | M32: =VLOOKUP(L32, GLOSSARY!$A:$C, 2, FALSE) -> VINEYARD PEN | N32: AM
A33: E384 | B33: IMG 75, P.132-133 | C33: June 27, 1751 | D33: "Phibbah have the head ache violently had her head salt (as they call it) by Fulerwood Quasheba, a noted woman for such performance. Twas pretty much thus! They putt a bitt of stick amongst the hair over the forehead, almost as high as the crown of the head, and shrew it rout till the chin cracks or the hair roots for you hear it. Then fasten it well, chafing the forehead and head well with rum and fresh lime roots ground to power rubb'd over it also. If this be about Noon, the person must go to rest and by no means be disturb'd or spoke to till night. This (?) not to be loosed till morrow almost Noon. Phibbah says this was very painful, but when loos'd gave her ease for a day or two, btu after her pain return'd again." | F33: VINEYARD PHIBBAH FULLERWOOD QUASHEBA | G33: P309 P314 | H33: =CONCATENATE(F33,"(",G33,")") -> VINEYARD PHIBBAH FULLERWOOD QUASHEBA(P309 P314) | I33: ILLNESS | L33: L20 | M33: =VLOOKUP(L33, GLOSSARY!$A:$C, 2, FALSE) -> VINEYARD PEN | N33: AM
A34: E362 | B34: IMG 77, P. 136-137 | C34: July 1, 1751 | D34: "Wanicker, who is a Papah Negroe of a country called....has seen and been in company with Man Eaters, she has seen them boil men's flesh to eat and yet they said it was more sweet than hogs flesh. They most adire the flesh of yellow and Red people, such as Hugo & Sambo, for they say the flesh of Black people is bitter. Most admire the feet and hands, especially the hands thick of the hand, just by the wrist leading to the finger. That there are sveral such in the country, but privately, because not allowed, for if found out, they are banished the country, for the grandees think they would perhaps thief their children and eat them...That some will eat the flesh of those who die of diseases but the most part they privately thief sick children, or people as are in good order, or else, thief or buy on purpose." | F34: WANICKER | G34: P73 | H34: =CONCATENATE(F34,"(",G34,")") -> WANICKER(P73) | I34: MISCELLANEOUS | L34: L20 | M34: =VLOOKUP(L34, GLOSSARY!$A:$C, 2, FALSE) -> VINEYARD PEN | N34: AM
A35: E363 | B35: IMG 81, P. 144-145 | C35: July 6, 1751 | D35: "At night gave Marina some sugar, 4 bottles of rum, some beef and pepper pott, with 10 pints of corn made into fungi to treat the Negroes and especially her shipmates...at her house warming. They were very merry at Night. Mr. Markman's Caesar sang and drummed, Guy and Charles, Phibbah and Wanicker danced Congo, etc. Marina herself got very drunk, as well as many others. I sat up good part of the night seeing their tricks. Charles ate fire--struck his naked arm many times with the edge of a bill, very hard, yet received no harm." | F35: MARINA CAESAR GUY CHARLES PHIBBAH WANICKER | G35: P73 P7 P300 P301 P302 P303 | H35: =CONCATENATE(F35,"(",G35,")") -> MARINA CAESAR GUY CHARLES PHIBBAH WANICKER(P73 P7 P300 P301 P302 P303) | I35: RECREATION | L35: L20 | M35: =VLOOKUP(L35, GLOSSARY!$A:$C, 2, FALSE) -> VINEYARD PEN | N35: PM
A36: E313 | B36: IMG 92, P.166-167 | C36: July 17, 1751 | D36: "Much fear of Negroes revolting in this island. Never such ___ allowed, so little prevention used before." | H36: =CONCATENATE(F36,"(",G36,")") -> () | I36: REBELLION/UPRISING | L36: L20 | M36: =VLOOKUP(L36, GLOSSARY!$A:$C, 2, FALSE) -> VINEYARD PEN
A37: E459 | B37: IMG 112, P.205-206 | C37: September 11, 1751 | D37: "Dark and cloudy, about 6 in the morning began to blow very fresh at NNE, continued with drizzling rain, about 11 blew harder at NE and at noon blew a storm. The hard gusts the sea waters up like a mist...From 3pm to sunset blew a hurricane, attended with rain from NE to EES. Blew the hngles off the stables and boiling house and all the thatch off the copperage and trash house, burst open the great house windows that were secured by strnog bars, blew the weather boards and ridge boards off the great house etc, every room full of water. The jasmine tree by the tombs blown down and many of the orange trees cut of the rows before the great house. All the pomegranates in the garden blown down and everything torn to pieces almost. Plantane trees all presently down. About sunset, all the white people viz Mr. Dorrill, Ms. Anderson, Miss Molly Dorrill, Capt. Rivera de la Bruce, Mr. Peter Fookes, Mr. Samuel Mordener, & myself all leave the great house & shelter in the storehouse and hurricane house. About 11 pm return'd to the great house, went to bed, that is laid down. The wind rather abated by times in the night. By times in the night blew very hard as ever almost attended with hard rain and lightning but no thunder. Mr, Fookes so timorous that he sat up all night." | F37: THE OVERSEER WILLIAM DORRILL ELIZABETH ANDERSON THE PLANTER'S WIFE CAPTAIN RIVERA DE LA BRUCE PETER FOOKES SAMUEL MORDENDER | G37: P43 P45 P75 P76 P401 P402 P403 | H37: =CONCATENATE(F37,"(",G37,")") -> THE OVERSEER WILLIAM DORRILL ELIZABETH ANDERSON THE PLANTER'S WIFE CAPTAIN RIVERA DE LA BRUCE PETER FOOKES SAMUEL MORDENDER(P43 P45 P75 P76 P401 P402 P403 ) | I37: CALAMITY | L37: L4 | M37: =VLOOKUP(L37, GLOSSARY!$A:$C, 2, FALSE) -> SALT RIVER ESTATE | N37: AM/PM
A38: E459 | B38: IMG 113, P.206-207 | C38: September 12, 1751 | D38: "Continue to blow hard with hard rain about 9...wind come to SEW but presently went back to about ES towards noon more moderate with fair weather by intervals. About noon I walked down to the Barcadier...strange havoc there. Mordenner's House quite down, all the South wall (except about 11 feet) of hte New store house wash'd clean away and some of the East and West walls pretty much must thus! Two thirds of the lime wash'd quite away. All of the heavy timber float'd a long away up in a surprising manner. The Boards, staves and shingles blown about as if they wer efeathers. Most of the New Wharf wash'd away, vast wrecks of sea weed drove a long way upon the land. A heavy iron roller case carried a long way from where it lay and half buried in the sand. Mr. Dorrill says the sea has raged with greater fury than either in the years 1722 or 1744." | F38: THE OVERSEER WILLIAM DORRILL | G38: P43 75 | H38: =CONCATENATE(F38,"(",G38,")") -> THE OVERSEER WILLIAM DORRILL(P43 75 ) | I38: CALAMITY | L38: L59 | M38: =VLOOKUP(L38, GLOSSARY!$A:$C, 2, FALSE) -> THE BARCADIER | N38: AM/PM
A39: E459 | B39: IMG 113, P.206-207 | C39: September 13, 1751 | D39: "Fresh breezes continue, thunder to the Southward. Walk'd a long way by the Sea each side of the Barcadier, no birds stirring. Shot 2 snipes. Many fish thrown up dead upon the shore. Broke my pocket knife cutting a mangrove. In the afternoon went in a canoe with Mordenner to Mr. Beckford's Barcadier. Strnage havoc there. The mangroves along the sea side twisted to pieces and few leaves left in them, all of woods and mountains look open and bare and very ragged, the woods appear like our woods in England in the fall of the leaf, when about half down. In the evening not much wnd and the sea much fallen." | F39: THE OVERSEER SAMUEL MORDENNER | G39: P43 P402 | H39: =CONCATENATE(F39,"(",G39,")") -> THE OVERSEER SAMUEL MORDENNER(P43 P402 ) | I39: CALAMITY | L39: L59 | M39: =VLOOKUP(L39, GLOSSARY!$A:$C, 2, FALSE) -> THE BARCADIER | N39: AM/PM
A40: E538 | B40: IMG 114, P.208-209 | C40: September 16, 1751 | D40: "A little before dinner, walking in the Plantation [at Salt River] Mr. Dorrill offered me if I would accept to be overseer of Egypt Estate (he would give me 60 pounds per annum). I willingly accepted of it. About 2 pm I set out for Egypt on the horse Billy, guided by Salt River Quaco, got there by 4 PM. Went into the field, found 42 negroes clearing teh ground at Top Hill of trash. Quacoo & Morris mending the garden fence." | F40: THE OVERSEER WILLIAM DORRILL QUACOO MORRIS | G40: P43 P75 P298 P226 | H40: =CONCATENATE(F40,"(",G40,")") -> THE OVERSEER WILLIAM DORRILL QUACOO MORRIS(P43 P75 P298 P226) | I40: MISCELLANEOUS | L40: L4 | M40: =VLOOKUP(L40, GLOSSARY!$A:$C, 2, FALSE) -> SALT RIVER ESTATE | N40: PM
A41: E538 | B41: IMG 115, P.210-211 | C41: September 16, 1751 | D41: "John Filton did not come home til 8 at night, gave him his discharge wrote thus: Westmoreland 16 September: I have this day discharged Mr. John Filton from my service. Wm. Dorrill. And an order thus! Mr. John Filton, deliver up all the keys as also the estate and everything belonging to me to the bearer Thomas Thistlewood who I hope will take better care of the Estate than you have done. Yrs. Wm. Dorill, Salt River 16 September 1751 Rec'd the Boiling House, Curing house & Corn house keys." | F41: THE OVERSEER JOHN FILTON | G41: P43 P430 | H41: =CONCATENATE(F41,"(",G41,")") -> THE OVERSEER JOHN FILTON(P43 P430) | I41: MISCELLANEOUS | L41: L1 | M41: =VLOOKUP(L41, GLOSSARY!$A:$C, 2, FALSE) -> EGYPT ESTATE
A42: E537 | B42: IMG 117, P.214=215 | C42: September 19, 1751 | D42: "Employ'd as before, Sent out Belinda catching crabbs," | F42: BELINDA | G42: P429 | H42: =CONCATENATE(F42,"(",G42,")") -> BELINDA(P429) | I42: HUSBANDRY/LIVESTOCK/FISHING | L42: L1 | M42: =VLOOKUP(L42, GLOSSARY!$A:$C, 2, FALSE) -> EGYPT ESTATE | N42: AM
A43: E463 | B43: IMG 123, P.224-225 | C43: September 24, 1751 | D43: "At night cum Dido (a Creolian) sup lect. Virgo. 111." | F43: THE OVERSEER DIDO | G43: P43 P105 | H43: =CONCATENATE(F43,"(",G43,")") -> THE OVERSEER DIDO(P43 P105) | I43: SEX | L43: L1 | M43: =VLOOKUP(L43, GLOSSARY!$A:$C, 2, FALSE) -> EGYPT ESTATE | N43: AM
A44: E539 | B44: IMG 123, P.224-225 | C44: September 26, 1751 | D44: "Bella missing all day." | F44: BELLA | G44: P176 | H44: =CONCATENATE(F44,"(",G44,")") -> BELLA(P176) | I44: ESCAPE/TRUANCY | L44: L0 | M44: =VLOOKUP(L44, GLOSSARY!$A:$C, 2, FALSE) -> UNKNOWN | N44: AM/PM
A45: E464 | B45: IMG 123, P.224-225 | C45: September 27, 1751 | D45: "This mornign had several Negoes whipp'd for various crimes, as running away, failing bringing grass, being accessory t the boiling house being broke open, etc." | F45: THE OVERSEER | H45: =CONCATENATE(F45,"(",G45,")") -> THE OVERSEER() | I45: PUNISHMENT/VIOLENCE | L45: L1 | M45: =VLOOKUP(L45, GLOSSARY!$A:$C, 2, FALSE) -> EGYPT ESTATE | N45: AM
A46: E539 | B46: IMG 123, P.224-225 | C46: September 27, 1751 | D46: "Bella brought home by her husband Sam." | F46: BELLA BELLA'S HUSBAND SAM | G46: P176 P431 | H46: =CONCATENATE(F46,"(",G46,")") -> BELLA BELLA'S HUSBAND SAM(P176 P431) | I46: ESCAPE/TRUANCY | L46: L1 | M46: =VLOOKUP(L46, GLOSSARY!$A:$C, 2, FALSE) -> EGYPT ESTATE | N46: AM
A47: E606 | B47: IMG 123, P. 224-225 | C47: September 27, 1751 | D47: "This morning had several Negroes whipp'd for various crimes, as running away: failing bringing grass, beign accessory to the Boiling House being broke open." | F47: THE OVERSEER | G47: P43 | H47: =CONCATENATE(F47,"(",G47,")") -> THE OVERSEER(P43) | I47: PUNISHMENT/VIOLENCE | L47: L1 | M47: =VLOOKUP(L47, GLOSSARY!$A:$C, 2, FALSE) -> EGYPT ESTATE | N47: AM
A48: E463 | B48: IMG 124, P.226-227 | C48: September 28, 1751 | D48: "Gave Dido one bitt, last night cu, Illa Bis." | F48: THE OVERSEER DIDO | G48: P43 P105 | H48: =CONCATENATE(F48,"(",G48,")") -> THE OVERSEER DIDO(P43 P105) | I48: SEX | L48: L1 | M48: =VLOOKUP(L48, GLOSSARY!$A:$C, 2, FALSE) -> EGYPT ESTATE | N48: PM
A49: E463 | B49: IMG 124, P.226-227 | C49: September 29, 1751 | D49: "Last night cum Dido, Bis." | F49: THE OVERSEER DIDO | G49: P43 P105 | H49: =CONCATENATE(F49,"(",G49,")") -> THE OVERSEER DIDO(P43 P105) | I49: SEX | L49: L1 | M49: =VLOOKUP(L49, GLOSSARY!$A:$C, 2, FALSE) -> EGYPT ESTATE | N49: PM
A50: E607 | B50: IMG 124, P.226-227 | C50: September 29, 1751 | D50: "*Heard of a white man and the Negroes rising upon Capt. Leister. He afterwards told me the story himself." | F50: CAPTAIN LEISTER THE OVERSEER "THE NEGROES" ON CAPTAIN LEISTER'S ESTATE | G50: P472 P473 P43 | H50: =CONCATENATE(F50,"(",G50,")") -> CAPTAIN LEISTER THE OVERSEER "THE NEGROES" ON CAPTAIN LEISTER'S ESTATE(P472 P473 P43) | I50: REBELLION/UPRISING | L50: L64 | M50: =VLOOKUP(L50, GLOSSARY!$A:$C, 2, FALSE) -> CAPTAIN LESITER'S ESTATE | N50: AM
A51: E463 | B51: IMG 124, P.226-228 | C51: September 30, 1751 | D51: "Last night Dido somn per me." | F51: THE OVERSEER DIDO | G51: P43 P105 | H51: =CONCATENATE(F51,"(",G51,")") -> THE OVERSEER DIDO(P43 P105) | I51: SEX | L51: L1 | M51: =VLOOKUP(L51, GLOSSARY!$A:$C, 2, FALSE) -> EGYPT ESTATE | N51: PM
A52: E463 | B52: IMG 125, P.228-229 | C52: October 1, 1751 | D52: "Last night cum Dido." | F52: THE OVERSEER DIDO | G52: P43 P105 | H52: =CONCATENATE(F52,"(",G52,")") -> THE OVERSEER DIDO(P43 P105) | I52: SEX | L52: L1 | M52: =VLOOKUP(L52, GLOSSARY!$A:$C, 2, FALSE) -> EGYPT ESTATE | N52: PM
A53: E600 | B53: IMG 127, P.232-233 | C53: October 6, 1751 | D53: "Mr. Stone here shooting again. Discharg'd him from coming here without leave." | F53: JOHN STONE THE OVERSEER | G53: P64 P43 | H53: =CONCATENATE(F53,"(",G53,")") -> JOHN STONE THE OVERSEER(P64 P43) | I53: MISCELLANEOUS | L53: L1 | M53: =VLOOKUP(L53, GLOSSARY!$A:$C, 2, FALSE) -> EGYPT ESTATE | N53: AM
A54: E459 | B54: IMG 239-240 | C54: October 20, 1751 | D54: "Mr. Dorrill says the storm was universal, reach'd Barbados, St. Kitts, etc." | F54: WILLIAM DORRILL | G54: P75 | H54: =CONCATENATE(F54,"(",G54,")") -> WILLIAM DORRILL(P75) | I54: CALAMITY | M54: =VLOOKUP(L54, GLOSSARY!$A:$C, 2, FALSE) -> #N/A | N54: AM
A55: E174 | B55: IMG 134, P. 245-246 | C55: November 1, 1751 | D55: "Negroes upon Egypt Esate Belonging to William Dorrill, Esq." Women: Lucy, Phibbah, Jenny, Myrtilla, Agnes, Hagar, Little Mimber, Chrishea, Violet, Betty Girls: Ellin (Ebo), Dido( Creole) Children: Nagua, Accubah, Dido, Franke, Jenny On the estate 28 men, 6 boys, 26 women, 6 girls, 14 chiuldren = 80, 8 at Salt River, 1 Abigail runaway. 89 belongs the estate." | F55: LUCY PHIBBAH JENNY MYRTILLA AGNES CHRISHEA VIOLET NAGUA ACCUBAH DIDO FRANKE DIDO ELLIN BETTY | G55: P3 P7 P104 P97 P124 P126 P117 P207 P16 P105 P194 P105 P33 P134 | H55: =CONCATENATE(F55," (",G55,")") -> LUCY PHIBBAH JENNY MYRTILLA AGNES CHRISHEA VIOLET NAGUA ACCUBAH DIDO FRANKE DIDO ELLIN BETTY (P3 P7 P104 P97 P124 P126 P117 P207 P16 P105 P194 P105 P33 P134 ) | I55: INVENTORY/RECORDS | L55: L1 | M55: =VLOOKUP(L55, GLOSSARY!$A:$C, 2, FALSE) -> EGYPT ESTATE | N55: AM
A56: E129 | B56: IMG 137, P.251-252 | C56: November 11, 1751 | D56: Old Sybil bitt [sic] bitt with a spider in coffee ground which makes her delirious singing her country, etc." | F56: OLD SYBIL | G56: P177 | H56: =CONCATENATE(F56," (",G56,")") -> OLD SYBIL (P177) | I56: ILLNESS | L56: L1 | M56: =VLOOKUP(L56, GLOSSARY!$A:$C, 2, FALSE) -> EGYPT ESTATE | N56: AM
A57: E461 | B57: IMG 137, P.251-252 | C57: November 11, 1751 | D57: "Employed haughing cane: finish'd them in a very slight manner, not half as they should be." | F57: EGYPT FIELDHANDS | G57: P315 | H57: =CONCATENATE(F57,"(",G57,")") -> EGYPT FIELDHANDS(P315) | I57: LABOR | L57: l1 | M57: =VLOOKUP(L57, GLOSSARY!$A:$C, 2, FALSE) -> EGYPT ESTATE | N57: AM/PM
A58: E175 | B58: IMG 137, P.251 | C58: November 13, 1751 | D58: "Gave following 24 hands new bills, night: AMbo, Plato, Adam, Cyrus, Jimmy, Port Royal, Humphrey, Sampson, Frank, George, Davie, Basheba, Yabba, Old Moll, Chrishea, Hannah, Lucy, Mirtilla, Marge, Bella, Jenny, Yara and Cynthia." | F58: AMBO PLATO ADAM CYRUS EGYPT JIMMY PORT ROYAL HUMPHREY SAMPSON FRANK GEORGE DAVIE BASHEBA YABBA OLD MOLL CHRISHEA HANNAH [EGYPT] LUCY MIRTILLA MARGE BELLA JENNY YARA CHRISHEA | G58: P170 P207 P208 P209 P210 P211 P212 P213 P214 P215 P216 P217 P218 P219 P220 P221 P222 P223 P224 P3 P126 P104 P97 | H58: =CONCATENATE(F58," (",G58,")") -> AMBO PLATO ADAM CYRUS EGYPT JIMMY PORT ROYAL HUMPHREY SAMPSON FRANK GEORGE DAVIE BASHEBA YABBA OLD MOLL CHRISHEA HANNAH [EGYPT] LUCY MIRTILLA MARGE BELLA JENNY YARA CHRISHEA (P170 P207 P208 P209 P210 P211 P212 P213 P214 P215 P216 P217 P218 P219 P220 P221 P222 P223 P224 P3 P126 P104 P97) | I58: INVENTORY/RECORDS | L58: L1 | M58: =VLOOKUP(L58, GLOSSARY!$A:$C, 2, FALSE) -> EGYPT ESTATE | N58: AM
A59: E130 | B59: IMG 139, P.255-256 | C59: November 15, 1751 | D59: "Sad murmuring amongst our Negroes perceove they have private encouragement at Salt River." | H59: =CONCATENATE(F59," (",G59,")") -> () | I59: REBELLION/UPRISING | L59: L1 L4 | M59: EGYPT ESTATE SALT RIVER ESTATE | N59: AM
A60: E463 | B60: IMG 143, P.263 | C60: November 25, 1751 | D60: "Last night Cum Dido sup me lect: remain Virgo. In the morning gave Dido a pair of glass ear dropps and a large glass bead becklace." | F60: THE OVERSEER DIDO | G60: P43 P105 | H60: =CONCATENATE(F60,"(",G60,")") -> THE OVERSEER DIDO(P43 P105) | I60: SEX | L60: L1 | M60: =VLOOKUP(L60, GLOSSARY!$A:$C, 2, FALSE) -> EGYPT ESTATE | N60: PM
A61: E540 | B61: IMG 142, P.261-262 | C61: November 25, 1751 | D61: "Betty and Hagar wanting." | F61: BETTY HAGAR | G61: P134 P82 | H61: =CONCATENATE(F61,"(",G61,")") -> BETTY HAGAR(P134 P82) | I61: ESCAPE/TRUANCY | L61: L0 | M61: =VLOOKUP(L61, GLOSSARY!$A:$C, 2, FALSE) -> UNKNOWN | N61: AM
A62: E540 | B62: IMG 143, P.263-264 | C62: November 26, 1751 | D62: "In the afternoon, I went to the hogstyes, found Old Tom there, brought him home; and Quacoo brought home Betty and Hagar." | F62: THE OVERSEER OLD TOM QUACOO BETTY HAGAR | G62: P43 P277 P298 P134 P82 | H62: =CONCATENATE(F62,"(",G62,")") -> THE OVERSEER OLD TOM QUACOO BETTY HAGAR(P43 P277 P298 P134 P82) | I62: ESCAPE/TRUANCY | L62: L1 | M62: =VLOOKUP(L62, GLOSSARY!$A:$C, 2, FALSE) -> EGYPT ESTATE | N62: PM
A63: E463 | B63: IMG 144, P.265-266 | C63: November 28, 1751 | D63: "Last night Dido somn al me." | F63: The OVERSEER DIDO | G63: P43 P105 | H63: =CONCATENATE(F63,"(",G63,")") -> The OVERSEER DIDO(P43 P105) | I63: SEX | L63: L1 | M63: =VLOOKUP(L63, GLOSSARY!$A:$C, 2, FALSE) -> EGYPT ESTATE | N63: PM
A64: E463 | B64: IMG 144, P.265-267 | C64: November 30, 1751 | D64: "At night cum Dido." | F64: The OVERSEER DIDO | G64: P43 P105 | H64: =CONCATENATE(F64,"(",G64,")") -> The OVERSEER DIDO(P43 P105) | I64: SEX | L64: L1 | M64: =VLOOKUP(L64, GLOSSARY!$A:$C, 2, FALSE) -> EGYPT ESTATE | N64: PM
A65: E463 | B65: IMG 144, P.265-267 | C65: December 1, 1751 | D65: "Last night cum Dido. R Virgo." | F65: The OVERSEER DIDO | G65: P43 P105 | H65: =CONCATENATE(F65,"(",G65,")") -> The OVERSEER DIDO(P43 P105) | I65: SEX | L65: L1 | M65: =VLOOKUP(L65, GLOSSARY!$A:$C, 2, FALSE) -> EGYPT ESTATE | N65: PM
A66: E463 | B66: IMG 145, P.267-268 | C66: December 2, 1751 | D66: "Last night Dido at Phibbah's house. In the morning gave her a trimming." | F66: DIDO PHIBBAH THE OVERSEER | G66: P105 P7 P43 | H66: =CONCATENATE(F66,"(",G66,")") -> DIDO PHIBBAH THE OVERSEER(P105 P7 P43) | I66: VISIT | L66: L1-U | M66: =VLOOKUP(L66, GLOSSARY!$A:$C, 2, FALSE) -> PHIBBAH'S HOUSE | N66: PM
A67: E465 | B67: IMG 146, P.269-270 | C67: December 5, 1751 | D67: "About half an hour before sunsett a large mock sun to the Southward of the sun." | H67: =CONCATENATE(F67,"(",G67,")") -> () | I67: ASTRONOMY | L67: L1 | M67: =VLOOKUP(L67, GLOSSARY!$A:$C, 2, FALSE) -> EGYPT ESTATE | N67: AM
A68: E541 | B68: IMG 146, P.269-270 | C68: December 5, 1751 | D68: "About half an hour before sunsett, a large Mock sun to the southward of the sun." | H68: =CONCATENATE(F68,"(",G68,")") -> () | I68: ASTRONOMY | L68: l1 | M68: =VLOOKUP(L68, GLOSSARY!$A:$C, 2, FALSE) -> EGYPT ESTATE | N68: PM
A69: E542 | B69: IMG 149, P.275-276 | C69: December 11, 1751 | D69: "Ambo and Cudjoe began to cutt the fences, began by Old Sarah's Hutt." | F69: AMBO CUDJOE | G69: P170 P52 | H69: =CONCATENATE(F69,"(",G69,")") -> AMBO CUDJOE(P170 P52) | I69: LABOR | L69: L1 | M69: =VLOOKUP(L69, GLOSSARY!$A:$C, 2, FALSE) -> EGYPT ESTATE | N69: AM
A70: E542 | B70: IMG 149, P.275-277 | C70: December 12, 1751 | D70: "Ambo and Cudjoe cutting fences as before." | F70: AMBO CUDJOE | G70: P170 P52 | H70: =CONCATENATE(F70,"(",G70,")") -> AMBO CUDJOE(P170 P52) | I70: LABOR | L70: L1 | M70: =VLOOKUP(L70, GLOSSARY!$A:$C, 2, FALSE) -> EGYPT ESTATE | N70: AM
A71: E601 | B71: IMG 150, P.277-278 | C71: December 17, 1751 | D71: "Jacob Ricketts and another gentleman call'd and told me he would prosecute me for whipping his NEgroes last Friday, as far as the law would allow." | F71: JACOB RICKETTS THE OVERSEER | G71: P464 P43 | H71: =CONCATENATE(F71,"(",G71,")") -> JACOB RICKETTS THE OVERSEER(P464 P43) | I71: MISCELLANEOUS | L71: L1 | M71: =VLOOKUP(L71, GLOSSARY!$A:$C, 2, FALSE) -> EGYPT ESTATE | N71: AM
A72: E542 | B72: IMG 151, P.279-280 | C72: December 20, 1751 | D72: "Ambo and Cudjoe cutting fences as they have been every working day since the first." | F72: AMBO CUDJOE | G72: P170 P52 | H72: =CONCATENATE(F72,"(",G72,")") -> AMBO CUDJOE(P170 P52) | I72: LABOR | L72: L1 | M72: =VLOOKUP(L72, GLOSSARY!$A:$C, 2, FALSE) -> EGYPT ESTATE | N72: AM
A73: E469 | B73: IMG 153. P.283-284 | C73: December 26, 1751 | D73: "The Negroes drumming and dancing all night long." | F73: EGYPT FIELDHANDS | G73: P315 | H73: =CONCATENATE(F73,"(",G73,")") -> EGYPT FIELDHANDS(P315) | I73: RECREATION | L73: L1-B | M73: =VLOOKUP(L73, GLOSSARY!$A:$C, 2, FALSE) -> EGYPT ESTATE NEGROE HOUSES | N73: PM
A74: E536 | B74: IMG 155, P.287-288 | C74: December 31, 1751 | D74: "Ambo and Cudjoe finished cutting fences about the home pasture. Sent them next to that by Tony's watch hutt." | F74: AMBO CUDJOE TONY | G74: P170 P52 P411 | H74: =CONCATENATE(F74,"(",G74,")") -> AMBO CUDJOE TONY(P170 P52 P411) | I74: LABOR | L74: L1 | M74: =VLOOKUP(L74, GLOSSARY!$A:$C, 2, FALSE) -> EGYPT ESTATE | N74: AM
A75: E608 | B75: IMG 44, P.42 | C75: February 17, 1752 | D75: "Old Tom and Ambo distilling low wines." | F75: OLD TOM AMBO | G75: P277 P170 | H75: =CONCATENATE(F75,"(",G75,")") -> OLD TOM AMBO(P277 P170) | I75: SPECIAL SKILL/TALENT | L75: L1 | M75: =VLOOKUP(L75, GLOSSARY!$A:$C, 2, FALSE) -> EGYPT ESTATE | N75: AM
A76: E608 | B76: IMG 45, P.43 | C76: February 18, 1752 | D76: "Old Tom and Ambo distilling rum." | F76: OLD TOM AMBO | G76: P277 P170 | H76: =CONCATENATE(F76,"(",G76,")") -> OLD TOM AMBO(P277 P170) | I76: SPECIAL SKILL/TALENT | L76: L1 | M76: =VLOOKUP(L76, GLOSSARY!$A:$C, 2, FALSE) -> EGYPT ESTATE | N76: AM
A77: E360 | B77: IMG 49, P.47 | C77: February 22, 1752 | D77: "Sent Lucy sick to Salt River." | F77: EGYPT LUCY | G77: P3 | H77: =CONCATENATE(F77,"(",G77,")") -> EGYPT LUCY(P3) | I77: ILLNESS | L77: L4 | M77: =VLOOKUP(L77, GLOSSARY!$A:$C, 2, FALSE) -> SALT RIVER ESTATE | N77: AM
A78: E703 | B78: IMG 51, P.49 | C78: February 24, 1752 | D78: "In the evening gave Jenny a new handkerchief." | F78: THE OVERSEER JENNY | G78: P43 P104 | I78: SUPPLY/LOAN/GIFT EXCHANGE | L78: L1 | M78: =VLOOKUP(L78, GLOSSARY!$A:$C, 2, FALSE) -> EGYPT ESTATE | N78: PM
A79: E703 | B79: IMG 71, P.69 | C79: March 14, 1752 | D79: "Jenny pretends to be young with child." | F79: JENNY | G79: P104 | I79: PREGNANCY/BIRTH | L79: L1 | M79: =VLOOKUP(L79, GLOSSARY!$A:$C, 2, FALSE) -> EGYPT ESTATE | N79: AM/PM
A80: E703 | B80: IMG 73, P.71 | C80: March 15, 1752 | D80: "Note: Jenny's face and belly is very much mark'd, she says she was a Grande man's pickaninny: that he had a horsem, cattle, etc & slaves of his own, that she was stole when he was not at home." | F80: JENNY | G80: P104 | I80: MISCELLANEOUS | L80: L1 | M80: =VLOOKUP(L80, GLOSSARY!$A:$C, 2, FALSE) -> EGYPT ESTATE | N80: AM/PM
A81: E682 | B81: IMG 75, P.73 | C81: March 17, 1752 | D81: "Rec'd by Joe a letter of yesterday's date from Mr. Charles McIntosh with six vomitts and a phiall of liquid laudanum." | F81: JOE CHARLES MCINTOSH THE OVERSEER | G81: P299 P516 P43 | H81: =CONCATENATE(F81,"(",G81,")") -> JOE CHARLES MCINTOSH THE OVERSEER(P299 P516 P43) | I81: MISCELLANEOUS | L81: L1 | M81: =VLOOKUP(L81, GLOSSARY!$A:$C, 2, FALSE) -> EGYPT ESTATE | N81: AM
A82: E703 | B82: IMG 149, P.147 | C82: June 7, 1752 | D82: "For a knife which I gave Jenny, 1 bitt. For a yard of white osnaburg, 2 bitts." | F82: THE OVERSEER JENNY | G82: P43 P104 | I82: INVENTORY/RECORDS | L82: L1 | M82: =VLOOKUP(L82, GLOSSARY!$A:$C, 2, FALSE) -> EGYPT ESTATE | N82: AM/PM
A83: E703 | B83: IMG 159, P.157 | C83: June 17, 1752 | D83: "Gave Jenny a piece of osnaburg to make her a pocket." | F83: THE OVERSEER JENNY | G83: P43 P104 | I83: SUPPLY/LOAN/GIFT EXCHANGE | L83: L1 | M83: =VLOOKUP(L83, GLOSSARY!$A:$C, 2, FALSE) -> EGYPT ESTATE | N83: AM/PM
A84: E703 | B84: IMG 165, P.163 | C84: June 22, 1752 | D84: "Gave Jenny 20 mackerell over and above for herself." | F84: THE OVERSEER JENNY | G84: P43 P104 | I84: SUPPLY/LOAN/GIFT EXCHANGE | L84: L1 | M84: =VLOOKUP(L84, GLOSSARY!$A:$C, 2, FALSE) -> EGYPT ESTATE | N84: AM/PM
A85: E703 | B85: IMG 166, P.164 | C85: June 23, 1752 | D85: "Cum Jenny sup book chest in my room about 11 am." | F85: the OVERSEER JENNY | G85: P43 P104 | I85: SEX | L85: L1 | M85: =VLOOKUP(L85, GLOSSARY!$A:$C, 2, FALSE) -> EGYPT ESTATE | N85: AM
A86: E610 | B86: IMG 182, P.180 | C86: July 23, 1752 | D86: "Saw a Negroe girl there, stung with a scorpion in the arm. It fell from a trash absket upon her, she complain'd much. Another Negroe took the scorpion and rubb'd the place with it and she was soon easy." | F86: "A NEGROE GIRL" | G86: P474 | H86: =CONCATENATE(F86,"(",G86,")") -> "A NEGROE GIRL"(P474) | I86: MISCELLANEOUS | M86: =VLOOKUP(L86, GLOSSARY!$A:$C, 2, FALSE) -> #N/A
A87: E361 | B87: IMG 204, P.202 | C87: October 1, 1752 | D87: "Sent Joe to Salt River for corn, sent by him 23 eggs and Accubbah, who going to learn to sew. | F87: JOE ACCUBAH | G87: P299 P16 | H87: =CONCATENATE(F87,"(",G87,")") -> JOE ACCUBAH(P299 P16) | I87: LABOR | J87: COOBAH | L87: L4 | M87: =VLOOKUP(L87, GLOSSARY!$A:$C, 2, FALSE) -> SALT RIVER ESTATE | N87: AM
A88: E550 | B88: IMG 217, P.215 | C88: October 27, 1752 | D88: "In the evening, Phibbah beginning to complain, sent Joe to Salt River with a mule for a midwife, int he night he return'd with Old Daphne. And Phibbah presently brought to bed of a girl." | F88: PHIBBAH THE OVERSEER JOE OLD DAPHNE | G88: P7 P43 P299 P11 | H88: =CONCATENATE(F88,"(",G88,")") -> PHIBBAH THE OVERSEER JOE OLD DAPHNE(P7 P43 P299 P11) | I88: PREGNANCY/BIRTH | L88: L1 | M88: =VLOOKUP(L88, GLOSSARY!$A:$C, 2, FALSE) -> EGYPT ESTATE | N88: PM
A89: E550 | B89: IMG 217, P.215 | C89: October 30, 1752 | D89: "Came a girl from Salt River nam'd Damsel to give Phibbah's child suck." | F89: DAMSEL PHIBBAH'S DAUGHTER | G89: P34 P433 | H89: =CONCATENATE(F89,"(",G89,")") -> DAMSEL PHIBBAH'S DAUGHTER(P34 P433) | I89: CHILDCARE | L89: L1 | M89: =VLOOKUP(L89, GLOSSARY!$A:$C, 2, FALSE) -> EGYPT ESTATE | N89: AM
A90: E550 | B90: IMG 218, P.216 | C90: October 31, 1752 | D90: "Damsel return'd home." | F90: DAMSEL | G90: P34 | H90: =CONCATENATE(F90,"(",G90,")") -> DAMSEL(P34) | I90: CHILDCARE | L90: L4 | M90: =VLOOKUP(L90, GLOSSARY!$A:$C, 2, FALSE) -> SALT RIVER ESTATE | N90: AM
A91: E550 | B91: IMG 220, P.218 | C91: November 3, 1752 | D91: "Gave Phibbah another quart bottle of rum and some sugar, which is second time since she was brought to bed." | F91: THE OVERSEER PHIBBAH | G91: P43 P7 | H91: =CONCATENATE(F91,"(",G91,")") -> THE OVERSEER PHIBBAH(P43 P7) | I91: SUPPLY/LOAN/GIFT EXCHANGE | L91: L1 | M91: =VLOOKUP(L91, GLOSSARY!$A:$C, 2, FALSE) -> EGYPT ESTATE | N91: AM
A92: E550 | B92: IMG 220, P.218 | C92: November 3, 1752 | D92: "Phibbah's child died." | F92: PHIBBAH'S DAUGHTER | G92: P433 | H92: =CONCATENATE(F92,"(",G92,")") -> PHIBBAH'S DAUGHTER(P433) | I92: DEATH | L92: L1 | M92: =VLOOKUP(L92, GLOSSARY!$A:$C, 2, FALSE) -> EGYPT ESTATE | N92: AM
A93: E550 | B93: IMG 220, P.218 | C93: November 3, 1752 | D93: "Old Daphne return'd home to Salt River." | F93: OLD DAPHNE | G93: P11 | H93: =CONCATENATE(F93,"(",G93,")") -> OLD DAPHNE(P11) | I93: CHILDCARE | L93: L4 | M93: =VLOOKUP(L93, GLOSSARY!$A:$C, 2, FALSE) -> SALT RIVER ESTATE | N93: AM
A94: E314 | B94: IMG 248, P.244 | C94: December 22, 1752 | D94: "Quashe extreme[ly] impudent and saucy, threatens my life, etc." | F94: THE OVERSEER QUASHE | G94: P285 P43 | H94: =CONCATENATE(F94,"(",G94,")") -> THE OVERSEER QUASHE(P285 P43) | I94: PUNISHMENT/VIOLENCE | L94: L1 | M94: =VLOOKUP(L94, GLOSSARY!$A:$C, 2, FALSE) -> EGYPT ESTATE | N94: AM
A95: E640 | B95: IMG 251-254, P. 247-250 | C95: December 27, 1752 | D95: "In the evening, walked to Tony's gate etc, killed a black snake by the Styx Bridge. Thence walked towards Paradise cane pieces, but a little before I got to Cabaritta Bridge, just at the small causeway end in the little morass (about sunset). Met Congo Sam, who has been runaway since the 2nd. Instant attempting to take him, he immediately struck at me with a backed bill he had in his hand, and repeated his chops with all vehemence driving me back into the morass towards the river 25 or 30 yards from the road, but through the great mercy of God, his blows either fell short of me or were warded off with a pimento stick I had in in jmy hand with which I sometimes got a good strike at him. And although yet, as pleased God, I received no harm; the bill being new was not very sharp. But what the most showed his intention was when I kept him off with my stick saying 'You villagin runaway, away with you, etc,' he answered in the Negro manner, 'I will kill you, I will kill you,' etc. I called out 'Murder, and help for God's sake,' very loud, but no assistance came so that I had no prospect but to lose my life, till I threw myself at him and fortunately seized hold of the blade of the bill. (Since he made the first chip at me, to this time, might be 5 or 6 minutes). He kept fast hold of the stock or handle. I endeavored to draw him into the road; he went readily, but would not go homewards. We went in this manner, over Cabaritta Bridge till we came against the watch hut then he would go no further. Bella & abigail there but would not assist me. (He spoke to them in his language and I wa smuch afraid of them). We might stand against the hut 6 or 8 minutes, nobody came. At last, he suddenly quitted his hold and threw himself into the river. I being possessed of the bill, leaped in after him, made 3 or 4 chops at him and the bill flew out of my hand into the water. He endeavoring to get it, I enclosed him and a stake in my arms, resolving to keep my holf (up to the breeches, waistband in water). 5 Negro men and 3 women, strangers, went over the bridge and would by no means assist me neither for threat nor promises, one saying he was sick, the others that they were in a hurry. After we had stood in this manner maybe 8 or 10 minutes, London came and assisted me; tied his hands behind him with my handkerchief; but whilst I was seeking my stick in the morass, which I had quitted whne I seized hold of the blade of the bill, London, having a load of provisions on his head, Sam got away into the bushes, where he by some means had his hands loosed and lost my handkerchief. Presently, London called out that Sam had seized his machete and would kill him. Two gentlemen being just rode by towards the bridge, I ran after them annd begged their assistance, being afraid to continues into the bush for it now began to be pretty dark. They went back on the road with me [London...] I secured his hands with my garters, took [him prisoner], I guarded him home, put him safe in irons 0and a] watch put over him." | F95: THE OVERSEER CONGO SAM LONDON ABIGAIL BELLA | G95: P43 P404 P249 P118 P176 | H95: =CONCATENATE(F95,"(",G95,")") -> THE OVERSEER CONGO SAM LONDON ABIGAIL BELLA(P43 P404 P249 P118 P176) | I95: REBELLION/UPRISING | L95: L15 | M95: =VLOOKUP(L95, GLOSSARY!$A:$C, 2, FALSE) -> WILDERNESS | N95: PM
A96: E640 | B96: IMG 255, P.251 | C96: December 27, 1752 | D96: "Note: last Friday, in the field Quashe told me (before all the NEgroes) that I should not eat much more meat here! I asking him if he meant to poison or murder me, after a pause, he replied neither, but he intended to invent some great lie and go and tell his master, to get me turned away, etc. Am also of the opinion London had no good intent when in the bush with Sam if he had not heard company coming with me. Have also reason to beleive that many of the Negroes, as Quashe, Ambo, Phibbah etc knew that Sam had an intent to murder me when we should meet, by what I heard them speak one day in the cookroom when I was in the back piazza reading." | F96: QUASHE THE OVERSEER AMBO PHIBBAH CONGO SAM | G96: P359 OR P284 P43 P170 P7 P404 | H96: =CONCATENATE(F96,"(",G96,")") -> QUASHE THE OVERSEER AMBO PHIBBAH CONGO SAM(P359 OR P284 P43 P170 P7 P404) | I96: REBELLION/UPRISING | L96: L1 | M96: =VLOOKUP(L96, GLOSSARY!$A:$C, 2, FALSE) -> EGYPT ESTATE
A97: E640 | B97: IMG 255-256, P.251-252 | C97: December 28, 1752 | D97: "In the morning had sam guarded by London to Salt River, related teh affair to Mr. Dorrill. Had him...handcuff'd and put in teh dungeon. Rode over to Mr., George Goode's and related the case to Colonel Rickett's and Mr. Lewis...is to start in the morning Eight o'clock at Mr. cook's Savanna la Mar and to have Sam there. Rode home and had Abigail and Bella given 100 lashes each." | F97: THE OVERSEER LONDON CONGO SAM WILLIAM DORRILL GEORGE. GOODE COLONEL RICKETT MR. LEWIS ABIGAIL BELLA | G97: P43 P404 P249 P75 P511 P512 P513 P118 P176 | H97: =CONCATENATE(F97,"(",G97,")") -> THE OVERSEER LONDON CONGO SAM WILLIAM DORRILL GEORGE. GOODE COLONEL RICKETT MR. LEWIS ABIGAIL BELLA(P43 P404 P249 P75 P511 P512 P513 P118 P176) | I97: PUNISHMENT/VIOLENCE | L97: L67 | M97: =VLOOKUP(L97, GLOSSARY!$A:$C, 2, FALSE) -> MR. GEORGE GOODE'S | N97: AM/PM
A98: E640 | B98: IMG 257, P.253 | C98: December 29, 1752 | D98: "Rode to Savanna la Mar, waited at Mr. William Cook's, for Mr. Lewis, about Noon he swore me and wrote Sam his mittimus and sent him to gaol. Congo Sharper brought him here." | F98: THE OVERSEER MR. LEWIS CONGO SAM CONGO SHARPER | G98: P43 P513 P404 P514 | H98: =CONCATENATE(F98,"(",G98,")") -> THE OVERSEER MR. LEWIS CONGO SAM CONGO SHARPER(P43 P513 P404 P514) | I98: PUNISHMENT/VIOLENCE | L98: L10 | M98: =VLOOKUP(L98, GLOSSARY!$A:$C, 2, FALSE) -> SAVANNA LA MAR | N98: AM
A99: E640 | B99: IMG 257, P.253 | C99: December 30, 1752 | D99: "Bella & Abigail wanting this morning. Sent out Plato to look for them." | F99: BELLA ABIGAIL PLATO | G99: P176 P118 P208 | H99: =CONCATENATE(F99,"(",G99,")") -> BELLA ABIGAIL PLATO(P176 P118 P208) | I99: ESCAPE/TRUANCY | L99: L0 | M99: =VLOOKUP(L99, GLOSSARY!$A:$C, 2, FALSE) -> UNKNOWN | N99: AM/PM
A100: E640 | B100: IMG 258, P.254 | C100: December 30, 1752 | D100: "Bella and Abigail come home from Salt River about 1 pm, having been there to complain." | F100: BELLA ABIGAIL | G100: P176 P118 | H100: =CONCATENATE(F100,"(",G100,")") -> BELLA ABIGAIL(P176 P118) | I100: ESCAPE/TRUANCY | L100: L1 | M100: =VLOOKUP(L100, GLOSSARY!$A:$C, 2, FALSE) -> EGYPT ESTATE | N100: PM
...

Sheet RELATIONSHIPS
A1: PERSON ID | B1: RELATION 'A' NAME | C1: ALT. NAMES | D1: RELATIONSHIP | E1: NAME | F1: RELATION IDS | G1: RELATION 'B' NAME | H1: BIOGRAPHICAL INFORMATION
A2: P1 | B2: MOLIA | C2: COOBAH | D2: MOTHER OF | E2: SILVIA | F2: P2 | G2: =VLOOKUP(F2, GLOSSARY!$A:$C, 2, FALSE) -> SILVIA | H2: Molia first appeared in the diary in December of 1761. Thistlewood purchased her in a group sale of five other Africans from a trader for 50 pounds. Upon her arrival to Egypt estate, he paired her with an enslaved fieldwoman named Wonga (also known as Princess) to be 'seasoned'. One week after her purchase, he put her to work in Egypt's fields. Four years following her purchase, Molia gave birth to a mixed race baby girl named Silvia. When Silvia was fifteen months old, Thistlewood hired Molia to labor on Masemure, a neighboring sugar plantation. He forced her to leave Silvia behind and in the care of Nanny, another enslaved mother of a little girl named Little Phibbah who was the same age as Silvia. Shortly after their separation, Silvia fell sick and died. Molia was never the same following Silvia's death. She never had any more children, and and she also refused to stay in place. Over the course of the next six years, she would run away no less than fourteen times. The seventh of these escapes was to a place called Bluefields Bay, to see a person Molia herself identified as a "Shipmate," a person who had survived the Middle Passage voyage with her to Jamaica. The fourteenth of these escapes (and the last that she would make in Jamaica) was to an estate called Paradise; it was the same estate where Molia had been sent to give birth to Silvia. Following this fourteenth recapture, Thistlewood sold Molia to another slave owner, who transported her away from Jamaica, and to the British colony of Savannah. Georgia.
A3: P1 | B3: MOLIA | C3: COOBAH | D3: HOUSEMATE OF | E3: PEGGY | F3: P19 | G3: =VLOOKUP(F3, GLOSSARY!$A:$C, 2, FALSE) -> PEGGY
A4: P1 | B4: MOLIA | C4: COOBAH | D4: SHIPMATE OF | E4: SHIPMATE | F4: P23 | G4: =VLOOKUP(F4, GLOSSARY!$A:$C, 2, FALSE) -> SHIPMATE
A5: P1 | B5: MOLIA | C5: COOBAH | D5: IGBO | E5: OGO | F5: P13 | G5: =VLOOKUP(F5, GLOSSARY!$A:$C, 2, FALSE) -> OGO
A6: P1 | B6: MOLIA | C6: COOBAH | D6: CAREGIVER OF/FOR | E6: ABBA | F6: P6 | G6: =VLOOKUP(F6, GLOSSARY!$A:$C, 2, FALSE) -> ABBA
A7: P1 | B7: MOLIA | C7: COOBAH | D7: GARDENER | G7: =VLOOKUP(F7, GLOSSARY!$A:$C, 2, FALSE) -> #N/A
A8: P1 | B8: MOLIA | C8: COOBAH | D8: SEASONEE OF | F8: P27 | G8: =VLOOKUP(F8, GLOSSARY!$A:$C, 2, FALSE) -> WANGA
A10: P2 | B10: SILVIA | D10: DAUGHTER OF | E10: MOLIA | F10: P1 | G10: =VLOOKUP(F10, GLOSSARY!$A:$C, 2, FALSE) -> MOLIA | H10: Silvia was born on November 12, 1766. Her mother was Molia, an "Ebo" woman presumed to have been 15 at the time of her capture into the slave trade, and 20 at the time of her birth. Silvia's father was never identified, although he was presumed by Thistlewood to have been a white man. For the first fifteen months of her life Silvia lived with her mother, and another enslaved young African woman named Peggy. In the winter of 1768, Thistlewood contracted Molia out to labor on a neighboring sugar estate named Masemure. He forced Molia to leave Silvia behind and in the care of another enslaved woman named Nanny, who also had a 1 year old daughter named Little Phibbah. Several months after her mother's departure, Silvia became sick, and died.
A12: P3 | B12: EGYPT LUCY | D12: MOTHER OF | E12: JULINA | F12: P4 | G12: =VLOOKUP(F12, GLOSSARY!$A:$C, 2, FALSE) -> JULINA | H12: Egypt Lucy was an Afro-Creole woman who labored on Egypt Estate's First gang for much of her life. She had two primary domestic partners: Daniel, a skilled enslaved laborer who lived on Egypt, and Mason Quashe a skilled enslaved laborer who belonged to Elizabeth Anderson--the quadroon mistress of William Dorrill, Thistlewood's first employer-- and who was a regular visitor at Egypt to perform various tasks of carpentry, masonry, and even supervision of the First Gang. Between 1750 and her death in 1772, Egypt Lucy had three confirmed pregnancies: one in October 1754 to her daughter Julina with Daniel, the second in August of 1758 to an unnamed son (presumably also with Daniel) who died at just 5 days old, and the third in November of 1759 to a son who was named Little Quashe (presumably after his father, Mason Quashe). In May 1760, Egypt became the wet nurse to John, the son of Egypt's housekeeper and Thistlewood. This seemed to mark the beginining of a strong and lasting friendship between not only Egypt Lucy and Phibbah, but between Egypt Lucy and Phibbah's broader social network of enslaved domestic workers. This circle included Phibbah's sister, Nancy,her daughter Accubah, an enslaved healer woman named Vine, and another enslaved domestic worker called House Franke. Together, the six women formed an agricutural co-op of sorts, pooling the money and resources they earned through the selling of goods they raised from their provison grounds, their raising of livestock, and from sewing work they were contracted to perform for whites. They intended the funds to be used to purchase at least one of each other's freedom. Egypt Lucy was relatively prosperous as a enslaved business woman; such that in 1769, she along with Phibbah, and House Franke gave Thistlewood a 27 pound loan to help him in his transition from Egypt's overseer to an independeny penkeeper of a property called Breadnut Island Pen. EGypt Lucy would als give Thistlewood a second personal loan of 10 pounds; he would go on to repay both loans within about a year. Following her stint as John's wetnurse, Egypt Lucy continued to act as a care provider and parental influence for both Phibbah's children. When Phibbah and Thistlewood moved away from Egypt and left John behind, they entrusted EGypt Lucy to escort him to their newhome on Breadnut Islabd Pen for visits. Egypt Lucy also kept abreast of the day-to-day and night-to-night activities of Phibbah's daughter Accubah--including her covert fasincination and involvement in the secret Myal society. On multiple occasions throughout the years, Egypt Lucy was chosen by her white masters to be a 'seasoner,' a role designed for mostly Afro-Creole enslaved men and women who had either been born or resided in Jamaica for extended periods of time to acclimate/'season' newly arrived Africans to their new realities. In December of 1761, after purchasing 6 new Africans from a slave trader named John Hutt, Thistlewood tasked Egpyt Lucy with being the seasoner of a young African girl included in this sale named Ogo (he would rename her Maria). In November of 1766, Ogo would give birth to her first child: a daughter named Lucy. In July 1770, shortly following Molia's fourth escape from and return to Breadnut Island Pen, Egypt Lucy paid a visit to the pen, where she interrupted Thistlewood's attempt to punish Molia by confining her to a set of bilboes, convincing him not to. As a field laborer, Egypt Lucy was frequently in poor health. In June of 1772, she died. Phibbah and a 12 year old John attended her funeral and burial.
A13: P3 | B13: EGYPT LUCY | D13: MOTHER OF | E13: LITTLE QUASHE | F13: P5 | G13: =VLOOKUP(F13, GLOSSARY!$A:$C, 2, FALSE) -> LITTLE QUASHE
A14: P3 | B14: EGYPT LUCY | D14: FRIEND OF | E14: PHIBBAH | F14: P7 | G14: =VLOOKUP(F14, GLOSSARY!$A:$C, 2, FALSE) -> PHIBBAH
A15: P3 | B15: EGYPT LUCY | D15: FRIEND OF | E15: NANCY | F15: P8 | G15: =VLOOKUP(F15, GLOSSARY!$A:$C, 2, FALSE) -> NANCY
A16: P3 | B16: EGYPT LUCY | D16: FRIEND OF | E16: HOUSE FRANKE | F16: P10 | G16: =VLOOKUP(F16, GLOSSARY!$A:$C, 2, FALSE) -> HOUSE FRANKE
A17: P3 | B17: EGYPT LUCY | D17: FRIEND OF | E17: VINE | F17: P12 | G17: =VLOOKUP(F17, GLOSSARY!$A:$C, 2, FALSE) -> VINE
A18: P3 | B18: EGYPT LUCY | D18: BUSINESS PARTNER OF | E18: PHIBBAH | F18: P7 | G18: =VLOOKUP(F18, GLOSSARY!$A:$C, 2, FALSE) -> PHIBBAH
A19: P3 | B19: EGYPT LUCY | D19: BUSINESS PARTNER OF | E19: HOUSE FRANKE | F19: P10 | G19: =VLOOKUP(F19, GLOSSARY!$A:$C, 2, FALSE) -> HOUSE FRANKE
A20: P3 | B20: EGYPT LUCY | D20: BUSINESS PARTNER OF | E20: NANCY | F20: P8 | G20: =VLOOKUP(F20, GLOSSARY!$A:$C, 2, FALSE) -> NANCY
A21: P3 | B21: EGYPT LUCY | D21: BUSINESS PARTNER OF | E21: COOBAH | F21: P16 | G21: =VLOOKUP(F21, GLOSSARY!$A:$C, 2, FALSE) -> COOBAH
A22: P3 | B22: EGYPT LUCY | D22: WETNURSE OF | E22: JOHN | F22: P9 | G22: =VLOOKUP(F22, GLOSSARY!$A:$C, 2, FALSE) -> JOHN
A23: P3 | B23: EGYPT LUCY | D23: CAREGIVER OF/FOR | E23: JOHN | F23: P9 | G23: =VLOOKUP(F23, GLOSSARY!$A:$C, 2, FALSE) -> JOHN
A24: P3 | B24: EGYPT LUCY | D24: GARDENER
A25: P3 | B25: EGYPT LUCY | D25: SEASONER TO | E25: OGO | F25: P13 | G25: =VLOOKUP(F25, GLOSSARY!$A:$C, 2, FALSE) -> OGO
A26: P3 | B26: EGYPT LUCY | D26: DOMESTIC PARTNER OF | E26: MASON QUASHE | F26: P25 | G26: =VLOOKUP(F26, GLOSSARY!$A:$C, 2, FALSE) -> MASON QUASHE
A27: P3 | B27: EGYPT LUCY | D27: DOMESTIC PARTNER OF | E27: DANIEL | F27: P42 | G27: =VLOOKUP(F27, GLOSSARY!$A:$C, 2, FALSE) -> DANIEL
A28: P3 | B28: EGYPT LUCY | D28: MOTHER OF | F28: P441 | G28: =VLOOKUP(F28, GLOSSARY!$A:$C, 2, FALSE) -> EGYPT LUCY'S CHILD #3
A29: P3 | B29: EGYPT LUCY | D29: FIELD GANG [FIRST] | F29: P105 | G29: DIDO
A30: P3 | B30: EGYPT LUCY | D30: FIELD GANG [FIRST] | F30: P134 | G30: BETTY
A31: P3 | B31: EGYPT LUCY | D31: FIELD GANG [FIRST] | F31: P27 | G31: WANGA
A32: P3 | B32: EGYPT LUCY | D32: FIELD GANG [FIRST] | F32: P33 | G32: ELLIN
A33: P3 | B33: EGYPT LUCY | D33: FIELD GANG [FIRST] | F33: P30 | G33: MOUNTAIN LUCY
A34: P3 | B34: EGYPT LUCY | D34: FIELD GANG [FIRST] | F34: P106 | G34: SARAH
A36: P4 | B36: JULINA | D36: DAUGHTER OF | E36: EGYPT LUCY | F36: P3 | G36: =VLOOKUP(F36, GLOSSARY!$A:$C, 2, FALSE) -> EGYPT LUCY | H36: Julina was born in October of 1754 on Egypt Estate. Her mother was Egypt Lucy, an enslaved and Afro-Creole member Egypt estate's first gang. Her father was Daniel, an enslaved skilled laborer who also lived on Egypt. In August of 1758, Julina's mother Egypt Lucy gave birth to an unnamed baby boy, Julina's brother, who died at 5 days old. The following year, in November of 1759, Egypt Lucy was sent away from Egypt to a neighboring estate called Paradise, where she gave birth to another son, Julina's second brother, who was named Little Quashe. Julina fell sick while her mother was away, but soon recovered. Little Quashe and Egypt Lucy returned to Egypt in January of 1760, where they would continue as one nuclear household. In October of 1766, Julina would, for reasons unspecified by Thistlewood, accompany Molia to Paradise for her lying in period before she gave birth to Silvia in November of that same year. In December of 1770, Julina became the mistress/concubine of a white man named Robert Parker, a friend of Thistlewood's.
A37: P4 | B37: JULINA | D37: SISTER OF | E37: LITTLE QUASHE | F37: P5 | G37: =VLOOKUP(F37, GLOSSARY!$A:$C, 2, FALSE) -> LITTLE QUASHE
A38: P4 | B38: JULINA | D38: CAREGIVER OF/FOR | E38: MOLIA | F38: P1 | G38: =VLOOKUP(F38, GLOSSARY!$A:$C, 2, FALSE) -> MOLIA
A39: P4 | B39: JULINA | D39: DOMESTIC PARTNER OF | F39: P69 | G39: MR. PARKER
A41: P5 | B41: LITTLE QUASHE | D41: SON OF | E41: EGYPT LUCY | F41: P3 | G41: =VLOOKUP(F41, GLOSSARY!$A:$C, 2, FALSE) -> EGYPT LUCY | H41: Little Quashe was born in November of 1759, the son of Egypt Lucy, a field laborer of Egypt Estate and Mason Quashe, a skilled enslaved laborer who belonged to Elizabeth Anderson--the quadroon mistress of William Dorrill, Thistlewood's first employer-- and who was a regular visitor at Egypt to perform various tasks of carpentry, masonry, and even supervision of the First Gang. He was half-brother to Julina, Egypt Lucy's first daughter. Like many children of his time and place, Little Quashe was frequently ill. He was cared for by his mother, as well as by his mother's close friends, Phibbah (the housekeeper of Egypt Estate), and Vine, an enslaved woman, healer and storyteller from a neighboring estate.
A42: P5 | B42: LITTLE QUASHE | D42: SON OF | F42: P25 | G42: =VLOOKUP(F42, GLOSSARY!$A:$C, 2, FALSE) -> MASON QUASHE
A43: P5 | B43: LITTLE QUASHE | D43: BROTHER OF | E43: JULINA | F43: P4 | G43: =VLOOKUP(F43, GLOSSARY!$A:$C, 2, FALSE) -> JULINA
A45: P6 | B45: ABBA | D45: MOTHER OF | E45: JOHNIE | F45: P20 | G45: =VLOOKUP(F45, GLOSSARY!$A:$C, 2, FALSE) -> ABBA'S JOHNIE | H45: Abba was an enslaved African young woman, first appearing in the diary in Februaryof 1758 when she was purchased by Thistlewood from a slave trader named John Parkinson for 46 pounds. Thistlewood intended for her to be a domestic worker, setting her to train in the cookroom with Egypt's housekeeper Phibbah, then hiring her out to other white neighbors throughout the parish. Abba would have several domestic/sexual partners over the course of the twenty eight years she appears in the diaries. The first of these was Hazat, a driver who belonged to William Mould, an owner of a neighboring plantation. Another was Cudjoe, an enslaved fieldhand who belonged to John Rickett, one of Thistlewood's friends. A third was Neptune, an enslaved man who belonged to a Savanna la Mar tavern owner and another of Thistlewood's friends, Thomas Emotson. A fourth was Lincoln, the very first enslaved person Thistlewood ever purcahsed. Abba was unique among the many enslaved women who appear in the diairies in the sense that was extremely fertile, having a total of thirteen pregnancies over the span of twenty eight years. Ten of these resulted in live births, one in a stillbirth. Of these ten children, six (Including Johnie, Neptune, Jenny, Mary)survived their first year of life and four survived until at least 1786, the year of Thistlewood's death and the last year of the diary records. Abba and her children's living arrangements fluctuated usually depending upon who her current sexual/domestic partner was, but for a period of time in 1767, she and Mary, Johnie and Neptune lived with Sally, a Congo woman who Thistlewood had first purchased as a 8 or 9 year old child in 1762. Abba was known to tell the Anansi spider stories that she had learned from her homeland alongside Vine, an enslaved domestic woman and healer from a neighboring plantation.
A46: P6 | B46: ABBA | D46: MOTHER OF | E46: MARY | F46: P21 | G46: =VLOOKUP(F46, GLOSSARY!$A:$C, 2, FALSE) -> ABBA'S MARY
A47: P6 | B47: ABBA | D47: MOTHER OF | F47: P442 | G47: =VLOOKUP(F47, GLOSSARY!$A:$C, 2, FALSE) -> JENNY [ABBA'S DAUGHTER]
A48: P6 | B48: ABBA | D48: MOTHER OF | F48: P443 | G48: =VLOOKUP(F48, GLOSSARY!$A:$C, 2, FALSE) -> NEPTUNE [ABBA'S SON]
A49: P6 | B49: ABBA | D49: HOUSEMATE OF | E49: SALLY | F49: P17 | G49: =VLOOKUP(F49, GLOSSARY!$A:$C, 2, FALSE) -> SALLY
A50: P6 | B50: ABBA | D50: DOMESTIC PARTNER OF | F50: P87 | G50: =VLOOKUP(F50, GLOSSARY!$A:$C, 2, FALSE) -> HAZAT
A51: P6 | B51: ABBA | D51: DOMESTIC PARTNER OF | F51: P24 | G51: =VLOOKUP(F51, GLOSSARY!$A:$C, 2, FALSE) -> LINCOLN
A52: P6 | B52: ABBA | D52: DOMESTIC PARTNER OF | F52: P444 | G52: =VLOOKUP(F52, GLOSSARY!$A:$C, 2, FALSE) -> CUDJOE [JOHN RICKETT'S]
A53: P6 | B53: ABBA | D53: DOMESTIC PARTNER OF | F53: P445 | G53: =VLOOKUP(F53, GLOSSARY!$A:$C, 2, FALSE) -> NEPTUNE [THOMAS EMOTSON'S]
A54: P6 | B54: ABBA | D54: AFRICAN | G54: =VLOOKUP(F54, GLOSSARY!$A:$C, 2, FALSE) -> #N/A
A55: P6 | B55: ABBA | D55: ANANSI STORYTELLER TO | F55: P12 | G55: =VLOOKUP(F55, GLOSSARY!$A:$C, 2, FALSE) -> VINE
G56: =VLOOKUP(F56, GLOSSARY!$A:$C, 2, FALSE) -> #N/A
A57: P7 | B57: PHIBBAH | C57: PHIB; PHIBBA | D57: MOTHER OF | E57: JOHN | F57: P9 | G57: =VLOOKUP(F57, GLOSSARY!$A:$C, 2, FALSE) -> JOHN | H57: Phibbah was the Afro-Creole housekeeper of Egypt Estate. She was owned by Molly Cope, the wife of John Cope, Thistlewood's employer. A prominent and influential figure among the broader enslaved communit, Phibbah often leveraged that influence to gain relative material and social benefits for herself, her children and her other loved ones. Phibbah was very close with a sister named Nancy who lived on a neighboring plantation and very frequently visited her. Phibbah had an unnamed enslaved husband, but this relationship was soon displaced by the sexual/domestic relationship she would strike up with Thistlewood that would last for over three decades, ending only in his death in 1786. Although he was never monogamous, Thistlewood referred to Phibbah as his "wife". The diaries depict Phibbah as having three confirmed pregnancies/children. The first was a daughter named Accubah [unknown date of birth and father; also called Coobah and later Jenny Young], a stillborn boy [with John Cope, born ] and John [her son with Thistlewood who lived to the age of 20]. Phibbah had a tight knit circle of friends, most of whom were enslaved women domestic laborers. These included her sister Nancy, her daughter Accubah, domestic laborer and healer Vine, and domestic laborer House Franke. Following the birth of her son John in 1760, she also became very close friends with an enslaved field woman of Egypt estate called Egypt Lucy who served as John's wetnurse. Phibbah often visited with Egypt Lucy, cared for her son Little Quashe when he was will. She also brought Egypt Lucy into the agricultural co-op network that she had formed with her sister, daughter and other friends. Together, the six women pooled the money and resources they earned through the selling of goods they raised from their provison grounds, their raising of livestock, and from sewing work they were contracted to perform for whites. They intended the funds to be used to purchase at least one of each other's freedom. Phibbah was a very prosperous businesswoman and in 1769, she along with Egypt Lucy, and House Franke gave Thistlewood a 27 pound loan to help him in his transition from Egypt's overseer to an independent penkeeper of a property called Breadnut Island Pen-- a loan that he would return about a year or so later. It was one of several loans she would give to them him throughout their relationship. Phibbah outlived Thistlewood, and was granted her freedom following his death in 1786.
A58: P7 | B58: PHIBBAH | C58: PHIB; PHIBBA | D58: MOTHER OF | E58: COOBAH | F58: P16 | G58: =VLOOKUP(F58, GLOSSARY!$A:$C, 2, FALSE) -> COOBAH
A59: P7 | B59: PHIBBAH | C59: PHIB; PHIBBA | D59: SISTER OF | E59: NANCY | F59: P8 | G59: =VLOOKUP(F59, GLOSSARY!$A:$C, 2, FALSE) -> NANCY
A60: P7 | B60: PHIBBAH | C60: PHIB; PHIBBA | D60: AUNT OF | F60: P446 | G60: =VLOOKUP(F60, GLOSSARY!$A:$C, 2, FALSE) -> DAVIE [NANCY'S SON]
A61: P7 | B61: PHIBBAH | C61: PHIB; PHIBBA | D61: AUNT OF | F61: P447 | G61: =VLOOKUP(F61, GLOSSARY!$A:$C, 2, FALSE) -> NANCY'S DAUGHTER
A62: P7 | B62: PHIBBAH | C62: PHIB; PHIBBA | D62: DOMESTIC PARTNER OF | F62: P436 | G62: =VLOOKUP(F62, GLOSSARY!$A:$C, 2, FALSE) -> PHIBBAH'S HUSBAND
A63: P7 | B63: PHIBBAH | C63: PHIB; PHIBBA | D63: FRIEND OF | E63: HOUSE FRANKE | F63: P10 | G63: =VLOOKUP(F63, GLOSSARY!$A:$C, 2, FALSE) -> HOUSE FRANKE
A64: P7 | B64: PHIBBAH | C64: PHIB; PHIBBA | D64: FRIEND OF | E64: VINE | F64: P12 | G64: =VLOOKUP(F64, GLOSSARY!$A:$C, 2, FALSE) -> VINE
A65: P7 | B65: PHIBBAH | C65: PHIB; PHIBBA | D65: FRIEND OF | E65: NANCY | F65: P8 | G65: =VLOOKUP(F65, GLOSSARY!$A:$C, 2, FALSE) -> NANCY
A66: P7 | B66: PHIBBAH | C66: PHIB; PHIBBA | D66: BUSINESS PARTNER OF | E66: HOUSE FRANKE | F66: P10 | G66: =VLOOKUP(F66, GLOSSARY!$A:$C, 2, FALSE) -> HOUSE FRANKE
A67: P7 | B67: PHIBBAH | C67: PHIB; PHIBBA | D67: BUSINESS PARTNER OF | E67: NANCY | F67: P8 | G67: =VLOOKUP(F67, GLOSSARY!$A:$C, 2, FALSE) -> NANCY
A68: P7 | B68: PHIBBAH | C68: PHIB; PHIBBA | D68: BUSINESS PARTNER OF | E68: COOBAH | F68: P16 | G68: =VLOOKUP(F68, GLOSSARY!$A:$C, 2, FALSE) -> COOBAH
A69: P7 | B69: PHIBBAH | C69: PHIB; PHIBBA | D69: NURSE OF/FOR | E69: LITTLE QUASHE | F69: P5 | G69: =VLOOKUP(F69, GLOSSARY!$A:$C, 2, FALSE) -> LITTLE QUASHE
A70: P7 | B70: PHIBBAH | C70: PHIB; PHIBBA | D70: NURSE OF/FOR | E70: EGYPT LUCY | F70: P3 | G70: =VLOOKUP(F70, GLOSSARY!$A:$C, 2, FALSE) -> EGYPT LUCY
G71: =VLOOKUP(F71, GLOSSARY!$A:$C, 2, FALSE) -> #N/A
A72: P8 | B72: NANCY | D72: SISTER OF | E72: PHIBBAH | F72: P7 | G72: =VLOOKUP(F72, GLOSSARY!$A:$C, 2, FALSE) -> PHIBBAH | H72: Nancy was an Afro-Creole domestic laborer who lived on/moved between Egypt estate, as well as Paradise estate (another plantation owned by John Cope. She was the sister of Phibbah, Egypt's housekeeper, and aunt to Phibbah's two children, Accubah [also known as Coobah and later Jenny Young] and John. The diaries confirm Nancy as having two pregnancies; one in to a boy named Davie who fell sick snd died in 1756, and another in 1757 to a girl who was born dead. Like Phibbah, Nancy held relative measures of material and social privilege. She held multiple 'balls' that her sister and other domestic enslaved labrers and whites attended. She was able to 'rent' out the labor of an enslaved Egypt fieldwoman named Rose to assist her in caring for Davie when he was ill. In the aftermath of Davie's death, Nancy held a "play" (funeral) for Davie that lasted for two days/nights. Nancy was close friends with her sister Phibbah, as well as a broader circle of friends that included ncluded her sister Phibbah, her niece Accubah, domestic laborer and healer Vine, domestic laborer House Franke, and fieldwoman Egypt Lucy. Together, the six women pooled the money and resources they earned through the selling of goods they raised from their provison grounds, their raising of livestock, and from sewing work they were contracted to perform for whites. They intended the funds to be used to purchase at least one of each other's freedom (notably, Nancy's).
A73: P8 | B73: NANCY | D73: BUSINESS PARTNER OF | E73: PHIBBAH | F73: P7 | G73: =VLOOKUP(F73, GLOSSARY!$A:$C, 2, FALSE) -> PHIBBAH
A74: P8 | B74: NANCY | D74: BUSINESS PARTNER OF | E74: HOUSE FRANKE | F74: P10 | G74: =VLOOKUP(F74, GLOSSARY!$A:$C, 2, FALSE) -> HOUSE FRANKE
A75: P8 | B75: NANCY | D75: BUSINESS PARTNER OF | E75: COOBAH | F75: P16 | G75: =VLOOKUP(F75, GLOSSARY!$A:$C, 2, FALSE) -> COOBAH
A76: P8 | B76: NANCY | D76: BUSINESS PARTNER OF | E76: EGYPT LUCY | F76: P3 | G76: =VLOOKUP(F76, GLOSSARY!$A:$C, 2, FALSE) -> EGYPT LUCY
A77: P8 | B77: NANCY | D77: FRIEND OF | E77: PHIBBAH | F77: P7 | G77: =VLOOKUP(F77, GLOSSARY!$A:$C, 2, FALSE) -> PHIBBAH
A78: P8 | B78: NANCY | D78: FRIEND OF | E78: HOUSE FRANKE | F78: P10 | G78: =VLOOKUP(F78, GLOSSARY!$A:$C, 2, FALSE) -> HOUSE FRANKE
A79: P8 | B79: NANCY | D79: FRIEND OF | E79: VINE | F79: P12 | G79: =VLOOKUP(F79, GLOSSARY!$A:$C, 2, FALSE) -> VINE
A80: P8 | B80: NANCY | D80: FRIEND OF | E80: EGYPT LUCY | F80: P3 | G80: =VLOOKUP(F80, GLOSSARY!$A:$C, 2, FALSE) -> EGYPT LUCY
A81: P8 | B81: NANCY | D81: AUNT OF | E81: COOBAH | F81: P16 | G81: =VLOOKUP(F81, GLOSSARY!$A:$C, 2, FALSE) -> COOBAH
A82: P8 | B82: NANCY | D82: AUNT OF | E82: JOHN | F82: P9 | G82: =VLOOKUP(F82, GLOSSARY!$A:$C, 2, FALSE) -> JOHN
A83: P8 | B83: NANCY | D83: MOTHER OF | F83: P446 | G83: =VLOOKUP(F83, GLOSSARY!$A:$C, 2, FALSE) -> DAVIE [NANCY'S SON]
A84: P8 | B84: NANCY | D84: MOTHER OF | F84: P447 | G84: =VLOOKUP(F84, GLOSSARY!$A:$C, 2, FALSE) -> NANCY'S DAUGHTER
G85: =VLOOKUP(F85, GLOSSARY!$A:$C, 2, FALSE) -> #N/A
A86: P9 | B86: JOHN | C86: MULATTO JOHN | D86: SON OF | E86: PHIBBAH | F86: P7 | G86: =VLOOKUP(F86, GLOSSARY!$A:$C, 2, FALSE) -> PHIBBAH | H86: John was the mixed race son of Phibbah, the housekeeper of Egypt Estate, and Thomas Thistlewood, Egypt's overseer and the later owner of Breadnut Island Pen. Although he assumed paternal and financial support for him, Thistlewood never directly acknowledged paternity of John in the diaries, either referring to him as "Phibbah's child" or "Mulatto John". John was born in April of 1760 in a difficult birth, assisted by a midwife from Salt River estate called Old Daphne and House Franke, his mother's close friend and business partner. In the days following his birth, John was nursed by an Egypt fieldwoman named Egypt Lucy, who would go on to become one of his mother's closest friends, business partners, and a caregiver for John when his parents moved away from him. Phibbah secured a promise from Thistlewood in October of 1761 that John would be granted his freedom and in May of 1762, he fulfilled that promise. During the majority of his childhood, the freed John was sent to live in a boarding school for mixed race children where he learned how to read and write, was eventually apprenticed to become a carpenter at the age of 15, and allowed to join in Jamaica's 'colored' militia. One of his childhood friends was James, the son of a mixed race domestic laborer named Little Mimber on a neighboring plantation. John was not diligent in his apprenticeship, often absenting from work for days on end. He was frequently in debt, and involved in domestic disputes. John lived to the age of twenty, then died in September of 1780 of a sudden, putrid stomach infection that turned his fingernails black and shredded his intestines. Phibbah was beside herself with grief, later suspecting that he had been poisoned as a result of a love triangle gone horribly wrong. The death struck a heavy blow to the broader enslaved community, many of whom came to his burial. John’s half-sister Accubah came to stay with their mother for several weeks afterwards.
A87: P9 | B87: JOHN | C87: MULATTO JOHN | D87: BROTHER OF | E87: COOBAH | F87: P16 | G87: =VLOOKUP(F87, GLOSSARY!$A:$C, 2, FALSE) -> COOBAH
A88: P9 | B88: JOHN | C88: MULATTO JOHN | D88: FRIEND OF | F88: P448 | G88: =VLOOKUP(F88, GLOSSARY!$A:$C, 2, FALSE) -> JAMES [LITTLE MIMBER'S SON]
A89: P9 | B89: JOHN | C89: MULATTO JOHN | D89: NEPHEW OF | F89: P8 | G89: =VLOOKUP(F89, GLOSSARY!$A:$C, 2, FALSE) -> NANCY
A90: P9 | B90: JOHN | C90: MULATTO JOHN | D90: DOMESTIC PARTNER OF
G91: =VLOOKUP(F91, GLOSSARY!$A:$C, 2, FALSE) -> #N/A
A92: P10 | B92: HOUSE FRANKE | D92: FRIEND OF | E92: PHIBBAH | F92: P7 | G92: =VLOOKUP(F92, GLOSSARY!$A:$C, 2, FALSE) -> PHIBBAH | H92: House Franke was an enslaved domestic laborer who lived on Paradise estate. She was a very close friend of Phibbah [the housekeeper of Egypt estate], Phibbah's sister Nancy, Phibbah's daughter Accubah [also known as Coobah and later, Jenny Young], an enslaved domestic laborer and healer named Vine, and an enslaved Egypt fieldwoman named Egypt Lucy. Together, the six women pooled the money and resources they earned through the selling of goods they raised from their provison grounds, their raising of livestock, and from sewing work they were contracted to perform for whites. They intended the funds to be used to purchase at least one of each other's freedom. House Franke had a husband named Paradise Jack who (presumably) lived with her at Paradise. House Franke was a very frequent visitor to Egypt, and to Breadnut Island Pen to visit with Phibbah. When Phibbah gave birth to John in 1760, House Franke came and stayed at Egypt for several days to assist at her bedside. When Phibbah herself fell ill, House Franke came and stayed with her again to nurse her back to health. Like Egypt Lucy, House Franke also mantained a significant presence in the lives of Phbbah's children (who did not live with her for the majority of the time). House Franke was a relatively prosperous businessowman and in 1769, she along with Phibbah, and Egypt Lucy gave Thistlewood a 27 pound loan to help him in his transition from Egypt's overseer to an independeny penkeeper of a property called Breadnut Island Pen. He would repay the loan about a year later. House Franke made a second loan to Thistlewood in December of 1770; he repaid it in September of 1771.
A93: P10 | B93: HOUSE FRANKE | D93: FRIEND OF | E93: EGYPT LUCY | F93: P3 | G93: =VLOOKUP(F93, GLOSSARY!$A:$C, 2, FALSE) -> EGYPT LUCY
A94: P10 | B94: HOUSE FRANKE | D94: FRIEND OF | E94: NANCY | F94: P8 | G94: =VLOOKUP(F94, GLOSSARY!$A:$C, 2, FALSE) -> NANCY
A95: P10 | B95: HOUSE FRANKE | D95: FRIEND OF | E95: VINE | F95: P12 | G95: =VLOOKUP(F95, GLOSSARY!$A:$C, 2, FALSE) -> VINE
A96: P10 | B96: HOUSE FRANKE | D96: BUSINESS PARTNER OF | E96: PHIBBAH | F96: P7 | G96: =VLOOKUP(F96, GLOSSARY!$A:$C, 2, FALSE) -> PHIBBAH
A97: P10 | B97: HOUSE FRANKE | D97: BUSINESS PARTNER OF | E97: COOBAH | F97: P12 | G97: =VLOOKUP(F97, GLOSSARY!$A:$C, 2, FALSE) -> VINE
A98: P10 | B98: HOUSE FRANKE | D98: BUSINESS PARTNER OF | E98: NANCY | F98: P8 | G98: =VLOOKUP(F98, GLOSSARY!$A:$C, 2, FALSE) -> NANCY
A99: P10 | B99: HOUSE FRANKE | D99: BUSINESS PARTNER OF | E99: EGYPT LUCY | F99: P3 | G99: =VLOOKUP(F99, GLOSSARY!$A:$C, 2, FALSE) -> EGYPT LUCY
A100: P10 | B100: HOUSE FRANKE | D100: NURSE OF/FOR | E100: PHIBBAH | F100: P7 | G100: =VLOOKUP(F100, GLOSSARY!$A:$C, 2, FALSE) -> PHIBBAH
A101: P10 | B101: HOUSE FRANKE | D101: DOMESTIC PARTNER OF | F101: P35 | G101: =VLOOKUP(F101, GLOSSARY!$A:$C, 2, FALSE) -> PARADISE JACK
G102: =VLOOKUP(F102, GLOSSARY!$A:$C, 2, FALSE) -> #N/A
A103: P11 | B103: OLD DAPHNE | D103: MIDWIFE TO | E103: PHIBBAH | F103: P7 | G103: =VLOOKUP(F103, GLOSSARY!$A:$C, 2, FALSE) -> PHIBBAH | H103: Old Daphne was an enslaved 'grannie' midwife who resided on Salt River Estate. She was called to preside over at least fivw different childbirths over the course of about a decade, including Phibbah, the housekeeper of Egypt estate and three enslaved fieldwomen named Jenny, Anjaw, Mountain Lucy and Sarah.
A104: P11 | B104: OLD DAPHNE | D104: MIDWIFE TO | F104: P104 | G104: =VLOOKUP(F104, GLOSSARY!$A:$C, 2, FALSE) -> JENNY
A105: P11 | B105: OLD DAPHNE | D105: MIDWIFE TO | F105: P166 | G105: =VLOOKUP(F105, GLOSSARY!$A:$C, 2, FALSE) -> ANJAW
...

Sheet Sheet5
A1: EVENT ID | B1: ARCHIVE ID(S) | C1: DATE(S) | D1: EVENT DESCRIPTION | E1: PERSON IDS | F1: NAMES | G1: PERSON IDS | H1: NAMES/PERSON IDS | I1: EVENT TYPE | J1: ALTERNATE NAMES | K1: LOCATION | L1: LOCATION ID | M1: VLOOKUP | N1: TIME OF DAY (AM/PM) | O1: WEATHER | P1: SPECIAL SKILL
A2: E1 | B2: IMG 178, P.172 | C2: July 7, 1766 | D2: "As my Nanny begins to be big, sent her to Paradise to lye in, as Mrs. Cope is so good as to promise to take care of any I send." | F2: NANNY THE PLANTER'S WIFE | G2: P15 P45 | H2: =CONCATENATE(F2," (",G2,")") -> NANNY THE PLANTER'S WIFE (P15 P45) | I2: PREGNANCY/BIRTH | J2: MOLLY COPE | L2: L2 | M2: =VLOOKUP(L2, GLOSSARY!$A:$C, 2, FALSE) -> PARADISE ESTATE | N2: AM
A3: E1 | B3: IMG 263, P.266 | C3: October 27, 1766 | D3: "Sent my Coobah to Paradise along with Julina, as she begins to be very big." | E3: MOLIA(P1); JULINA (P4) | F3: MOLIA JULINA | G3: P1 P4 | H3: =CONCATENATE(F3," (",G3,")") -> MOLIA JULINA (P1 P4) | I3: PREGNANCY/BIRTH | J3: COOBAH | K3: BREADNUT ISLAND PEN; PARADISE ESTATE | L3: L3; L2 | M3: =VLOOKUP(L3, GLOSSARY!$A:$C, 2, FALSE) -> #N/A | N3: AM
A4: E1 | B4: IMG 268, P.271 | C4: November 1, 1766 | D4: "This evening my Maria brought to bed of a girl at Paradise estate." | F4: OGO LITTLE LUCY | G4: P13 P14 | H4: =CONCATENATE(F4," (",G4,")") -> OGO LITTLE LUCY (P13 P14) | I4: PREGNANCY/BIRTH | L4: L2 | M4: =VLOOKUP(L4, GLOSSARY!$A:$C, 2, FALSE) -> PARADISE ESTATE | N4: PM
A5: E1 | B5: IMG 276, P. 279 | C5: November 12, 1766 | D5: "My Coobah brought to bed of a girl at Paradise Estate" | E5: MOLIA (P1); SILVIA (P2) | F5: MOLIA SILVIA | G5: P1 P2 | H5: =CONCATENATE(F5," (",G5,")") -> MOLIA SILVIA (P1 P2) | I5: PREGNANCY/BIRTH | J5: COOBAH | K5: PARADISE ESTATE | L5: L2 | M5: =VLOOKUP(L5, GLOSSARY!$A:$C, 2, FALSE) -> PARADISE ESTATE | N5: PM
A6: E1 | B6: IMG 280 | C6: November 17, 1766 | D6: "Maria & Coobah at Paradise lately brought to bed." | E6: MOLIA (P1); OGO (P13) | F6: MOLIA OGO | G6: P1 P13 | H6: =CONCATENATE(F6," (",G6,")") -> MOLIA OGO (P1 P13) | I6: PREGNANCY/BIRTH | J6: COOBAH, MARIA | K6: PARADISE ESTATE | L6: L2 | M6: =VLOOKUP(L6, GLOSSARY!$A:$C, 2, FALSE) -> PARADISE ESTATE | N6: AM
A7: E1 | B7: IMG 289, P.293 | C7: November 30, 1766 | D7: "My Maria come home from Paradise Estate." | F7: OGO LITTLE LUCY | G7: P13 P14 | H7: =CONCATENATE(F7," (",G7,")") -> OGO LITTLE LUCY (P13 P14) | I7: PREGNANCY/BIRTH | L7: L2 L1 | M7: PARADISE ESTATE EGYPT ESTATE | N7: AM
A8: E1 | B8: IMG 295, P.299 | C8: December 8, 1766 | D8: "My Cubbah [sic] come home from Paradise with her child x, does not seem a Negro, but Mulatto." | E8: MOLIA (P1) SILVIA (P2) | F8: MOLIA | G8: P1 | H8: =CONCATENATE(F8," (",G8,")") -> MOLIA (P1) | I8: PREGNANCY/BIRTH | J8: COOBAH | K8: BREADNUT ISLAND PEN | L8: L3 | M8: =VLOOKUP(L8, GLOSSARY!$A:$C, 2, FALSE) -> BREADNUT ISLAND PEN | N8: AM
A9: E1 | B9: IMG 12 | C9: January 3. 1767 | D9: "Paradise Quasheba (the grannie) here to day. Gave her 3 cobbs for looking after Nanny, Maria and Coobah." | E9: PARADISE QUASHEBA MOLIA OGO NANNY | F9: PARADISE QUASHEBA MOLIA OGO NANNY | G9: P18 P1 P13 P15 | H9: =CONCATENATE(F9," (",G9,")") -> PARADISE QUASHEBA MOLIA OGO NANNY (P18 P1 P13 P15) | I9: PREGNANCY/BIRTH | J9: COOBAH, MARIA | K9: BREADNUT ISLAND PEN | L9: L3 | M9: =VLOOKUP(L9, GLOSSARY!$A:$C, 2, FALSE) -> BREADNUT ISLAND PEN | N9: AM

Sheet JON RELATIONSHIPS
A1: PERSON ID | B1: NAME | C1: ALT. NAMES | D1: RELATIONSHIP | E1: RELATION IDS
A2: P1 | B2: Molia | C2: Coobah | D2: MOTHER | E2: P2 | F2: =VLOOKUP(E2,GLOSSARY!A:C,2,FALSE) -> SILVIA
A3: P1 | B3: Molia | C3: Coobah | D3: HOUSEMATE | E3: P19 | F3: =VLOOKUP(E3,GLOSSARY!A:C,2,FALSE) -> PEGGY
A4: P1 | B4: Molia | C4: Coobah | D4: SHIPMATE | E4: P23 | F4: =VLOOKUP(E4,GLOSSARY!A:C,2,FALSE) -> SHIPMATE
A5: P1 | B5: Molia | C5: Coobah | D5: IGBO | E5: P13 | F5: =VLOOKUP(E5,GLOSSARY!A:C,2,FALSE) -> OGO
A6: P1 | B6: Molia | C6: Coobah | D6: CAREGIVER | E6: P6 | F6: =VLOOKUP(E6,GLOSSARY!A:C,2,FALSE) -> ABBA
A7: P1 | B7: Molia | C7: Coobah | D7: GARDENER
A9: P2 | B9: Silvia | D9: DAUGHTER | E9: P1 | F9: =VLOOKUP(E9,GLOSSARY!A:C,2,FALSE) -> MOLIA
A11: P3 | B11: Egypt Lucy | D11: MOTHER | E11: P4 | F11: =VLOOKUP(E11,GLOSSARY!A:C,2,FALSE) -> JULINA
A12: P3 | B12: Egypt Lucy | D12: MOTHER | E12: P5 | F12: =VLOOKUP(E12,GLOSSARY!A:C,2,FALSE) -> LITTLE QUASHE
A13: P3 | B13: Egypt Lucy | D13: FRIEND | E13: P7 | F13: =VLOOKUP(E13,GLOSSARY!A:C,2,FALSE) -> PHIBBAH
A14: P3 | B14: Egypt Lucy | D14: FRIEND | E14: P8 | F14: =VLOOKUP(E14,GLOSSARY!A:C,2,FALSE) -> NANCY
A15: P3 | B15: Egypt Lucy | D15: FRIEND | E15: P10 | F15: =VLOOKUP(E15,GLOSSARY!A:C,2,FALSE) -> HOUSE FRANKE
A16: P3 | B16: Egypt Lucy | D16: FRIEND | E16: P12 | F16: =VLOOKUP(E16,GLOSSARY!A:C,2,FALSE) -> VINE
A17: P3 | B17: Egypt Lucy | D17: BUSINESS PARTNER | E17: P7 | F17: =VLOOKUP(E17,GLOSSARY!A:C,2,FALSE) -> PHIBBAH
A18: P3 | B18: Egypt Lucy | D18: BUSINESS PARTNER | E18: P10 | F18: =VLOOKUP(E18,GLOSSARY!A:C,2,FALSE) -> HOUSE FRANKE
A19: P3 | B19: Egypt Lucy | D19: BUSINESS PARTNER | E19: P8 | F19: =VLOOKUP(E19,GLOSSARY!A:C,2,FALSE) -> NANCY
A20: P3 | B20: Egypt Lucy | D20: BUSINESS PARTNER | E20: P16 | F20: =VLOOKUP(E20,GLOSSARY!A:C,2,FALSE) -> COOBAH
A21: P3 | B21: Egypt Lucy | D21: WETNURSE | E21: P9 | F21: =VLOOKUP(E21,GLOSSARY!A:C,2,FALSE) -> JOHN
A22: P3 | B22: Egypt Lucy | D22: CAREGIVER | E22: P9 | F22: =VLOOKUP(E22,GLOSSARY!A:C,2,FALSE) -> JOHN
A23: P3 | B23: Egypt Lucy | D23: GARDENER | F23: =VLOOKUP(E23,GLOSSARY!A:C,2,FALSE) -> #N/A
A24: P3 | B24: Egypt Lucy | D24: SEASONER | E24: P13 | F24: =VLOOKUP(E24,GLOSSARY!A:C,2,FALSE) -> OGO
A25: P3 | B25: Egypt Lucy | D25: DOMESTIC PARTNER | F25: =VLOOKUP(E25,GLOSSARY!A:C,2,FALSE) -> #N/A
A27: P4 | B27: Julina | D27: DAUGHTER | E27: P3 | F27: =VLOOKUP(E27,GLOSSARY!A:C,2,FALSE) -> EGYPT LUCY
A28: P4 | D28: SISTER | E28: P5 | F28: =VLOOKUP(E28,GLOSSARY!A:C,2,FALSE) -> LITTLE QUASHE
A29: P4 | D29: CAREGIVER | E29: P1 | F29: =VLOOKUP(E29,GLOSSARY!A:C,2,FALSE) -> MOLIA
F30: =VLOOKUP(E30,GLOSSARY!A:C,2,FALSE) -> #N/A
A31: P5 | B31: Little Quashe | D31: SON | E31: P3 | F31: =VLOOKUP(E31,GLOSSARY!A:C,2,FALSE) -> EGYPT LUCY
A32: P5 | D32: BROTHER | E32: P4 | F32: =VLOOKUP(E32,GLOSSARY!A:C,2,FALSE) -> JULINA
F33: =VLOOKUP(E33,GLOSSARY!A:C,2) -> #N/A
A34: P6 | B34: Abba | D34: MOTHER | E34: P20; P21 | F34: =VLOOKUP(E34,GLOSSARY!A:C,2) -> THE GOVERNOR'S WIFE
A35: P6 | D35: HOUSEMATE
A36: P6 | D36: AFRICAN
A37: P6 | D37: ANANSI STORYTELLER
A39: P7 | B39: Phibbah | C39: Phib, Phibba | D39: MOTHER
A40: P7 | D40: SISTER
A41: P7 | D41: AUNT
A42: P7 | D42: FRIEND
A43: P7 | D43: BUSINESS PARTNER
A44: P7 | D44: NURSE
A46: P8 | B46: Nancy | D46: SISTER
A47: P8 | D47: BUSINESS PARTNER
A48: P8 | D48: FRIEND
A49: P8 | D49: AUNT
A50: P8 | D50: MOTHER
A52: P9 | B52: John | C52: Mulatto John | D52: SON
A53: P9 | D53: BROTHER
A55: P10 | B55: House Franke | D55: FRIEND
A56: P10 | D56: BUSINESS PARTNER
A57: P10 | D57: NURSE
A59: P11 | B59: Old Daphne | D59: MIDWIFE
A61: P12 | B61: Vine | D61: NURSE
A62: P12 | D62: FRIEND
A63: P12 | D63: ANANSI STORYTELLER
A65: P13 | B65: Ogo | C65: Maria | D65: IGBO
A66: P13 | D66: MOTHER
A67: P13 | D67: NURSE
A68: P13 | D68: HOUSEMATE
A69: P13 | D69: SEASONEE
A70: P13 | D70: CAREGIVER
A72: P14 | B72: Lucy | C72: Little Lucy | D72: DAUGHTER
A74: P15 | B74: Nanny | D74: AFRICAN
A75: P15 | D75: MOTHER
A76: P15 | D76: CAREGIVER
A78: P16 | B78: Coobah | C78: Accubah; Jenny Young | D78: DAUGHTER
A79: P16 | D79: SISTER
A80: P16 | D80: MOTHER
A81: P16 | D81: BUSINESS PARTNER
A82: P16 | D82: MYAL PRACTITIONER
A84: P17 | B84: Sally | D84: CONGO
A85: P17 | D85: HOUSEMATE
A86: P17 | D86: GARDENER
A88: P18 | B88: Paradise Quasheba | D88: MIDWIFE
A90: P19 | B90: Peggy | D90: AFRICAN
A91: P19 | D91: SHIPMATE
A92: P19 | D92: HOUSEMATE
A93: P19 | D93: GARDENER
A95: P20 | B95: Johnie | D95: SON
A96: P20 | D96: BROTHER
A98: P21 | B98: Mary | D98: DAUGHTER
A99: P21 | D99: SISTER
A101: P22 | B101: Little Phibbah | D101: DAUGHTER
A102: P22 | D102: SISTER
A104: P23 | B104: Shipmate | D104: AFRICAN
A105: P23 | D105: SHIPMATE
A107: P24 | B107: Lincoln | D107: IGBO
D108: DOMESTIC PARTNER

Sheet LookUp
A1: Type of Relationship | B1: Event Type
A2: AFRICAN | B2: ANANSI
A3: ANANSI STORYTELLER TO | B3: ASTRONOMY
A4: AUNT OF | B4: BRITAIN
A5: BROTHER OF | B5: CALAMITY
A6: BUSINESS PARTNER OF | B6: CHILDCARE
A7: CAREGIVER OF/FOR | B7: DEATH
A8: CONGO | B8: DOMESTIC RELATIONS(HIPS)
A9: DAUGHTER OF | B9: ESCAPE/TRUANCY
A10: DOMESTIC PARTNER OF | B10: FAMILY/KINSHIP
A11: FATHER OF | B11: FREEDOM/MANUMISSION
A12: FIELD GANG [FIRST] | B12: GARDENING/AGRICULTURE
... A27: WETNURSE OF | B27: SALE
B28: SCHOOL
B29: SCRAMBLE
B30: SEASONING
B31: SEX
B32: SPECIAL SKILL/TALENT
B33: SUICIDE
B34: SUPERSTITION
B35: SUPPLY/GIFT EXCHANGE
B36: SUPPLY/LOAN/GIFT EXCHANGE
B37: VISIT
B38: WEATHER

Sheet JON EVENTS
A1: E1 | B1: IMG 263, P.266 | C1: October 27, 1766 | D1: "Sent my Coobah to Paradise along with Julina, as she begins to be very big." | E1: MOLIA(P1); JULINA (P4) | F1: PREGNANCY/BIRTH | G1: COOBAH | H1: BREADNUT ISLAND PEN; PARADISE ESTATE | I1: L3; L2 | J1: AM
A2: E2 | B2: IMG 276, P. 279 | C2: November 12, 1766 | D2: "My Coobah brought to bed of a girl at Paradise Estate" | E2: MOLIA (P1); SILVIA (P2) | F2: PREGNANCY/BIRTH | G2: COOBAH | H2: PARADISE ESTATE | I2: L2 | J2: PM
A3: E3 | B3: IMG 280 | C3: November 17, 1766 | D3: "Maria & Coobah at Paradise lately brought to bed." | E3: MOLIA (P1); OGO (P13) | F3: PREGNANCY/BIRTH | G3: COOBAH, MARIA | H3: PARADISE ESTATE | I3: L2 | J3: AM
A4: E4 | B4: IMG 295, P.299 | C4: December 8, 1766 | D4: "My Cubbah [sic] come home from Paradise with her child x, does not seem a Negro, but Mulatto." | E4: MOLIA (P1) SILVIA (P2) | F4: PREGNANCY/BIRTH | G4: COOBAH | H4: BREADNUT ISLAND PEN | I4: L3 | J4: AM
B5: IMG 12 | C5: January 3. 1767 | D5: "Paradise Quasheba (the grannie) here to day. Gave her 3 cobbs for looking after Nanny, Maria and Coobah." | E5: P18; P1, P13, P15 | F5: PREGNANCY/BIRTH | G5: COOBAH, MARIA | H5: BREADNUT ISLAND PEN | I5: L3 | J5: AM
A6: E9 | B6: IMG 15, P.10 | C6: January 5. 1767 | D6: "Maria and Cubbah in Egypt Field" | E6: MOLIA (P1); OGO (P13) | F6: LABOR | G6: CUBBAH; MARIA | H6: EGYPT | I6: L1 | J6: AM
A7: E15 | B7: IMG 242, P.237 | C7: October 6, 1767 | D7: "Sent Coobah to Egypt to have her child, yaws dropped." | E7: MOLIA (P1) | F7: PREGNANCY/BIRTH | G7: COOBAH | H7: EGYPT ESTATE | I7: L1 | J7: AM
A8: E15 | B8: IMG 242, P.237 | C8: October 6, 1767 | D8: "Sent Coobah to Egypt to have her child, yaws dropped." | E8: MOLIA (P1) | F8: DEATH | G8: COOBAH | H8: EGYPT ESTATE | I8: L1 | J8: AM
A9: E15 | B9: IMG 244, P.239 | C9: October 8, 1767 | D9: "My Coobah come home from Egypt." | E9: MOLIA (P1) | F9: PREGNANCY/BIRTH | G9: COOBAH | H9: BREADNUT ISLAND PEN | I9: L3 | J9: AM
A10: E10 | B10: IMG 24, P. 19 | C10: January 23, 1768 | D10: "At 8AM set out upon Prince horse, rode to Masemure, Capt Arthur Forest's to see if they wanted to hire Negroes, staid [sic] about an hour with David Kinlock, got home before Noon." | E10: THE OVERSEER; ARTHUR FOREST; DAVID KINLOCK | F10: LABOR | G10: THOMAS THISTLEWOOD | H10: MASEMURE ESTATE | I10: L6 | J10: AM
A11: E10 | B11: IMG 36, P. 31 | C11: February 9, 1768 | D11: "P.M. Wrote to Mr. David Kinlock, at Masemure Estate, and sent Dick, Coobah and Maria there to work, to be ready to go in the field tomorrow morning: Made Coobah leave her child with Nanny, gave a bitt and 4 herrings each." | E11: THE OVERSEER (P43); DAVID KINLOCK (P48); SAWNO (P39) OGO (P13) MOLIA (P1) NANNY (P15) SILVIA (P2) | F11: LABOR | G11: THOMAS THISTLEWOOD DICK MARIA COOBAH | H11: MASEMURE ESTATE | I11: L6 | J11: PM
A12: E10 | B12: IMG 46, P. 41 | C12: February 29, 1768 | D12: "Nanny minding Coobah's child. Should be 14 of my Negroes at Masemure" | E12: NANNY (P15) SILVIA (P2) | F12: CHILDCARE | H12: BREADNUT ISLAND PEN | I12: L3 | J12: AM
A13: E10 | B13: IMG 52, P.47 | C13: March 14, 1768 | D13: "In evening received a letter from Mr. David Kinlock by Coobah, whose child is sick." | E13: DAVID KINLOCK (P48) THE OVERSEER (P43) MOLIA (P1) | F13: CHILDCARE | G13: THOMAS THISTLEWOOD COOBAH | H13: BREADNUT ISLAND PEN | I13: L3 | J13: PM
A14: E10 | B14: IMG 53, P.48 | C14: March 16, 1768 | D14: "Coobah's child Silvia died; had it buried." | E14: SILVIA (P2) | F14: DEATH | H14: BREADNUT ISLAND PEN | I14: L3 | J14: AM
A15: E10 | B15: IMG 53, P.48 | C15: March 17, 1768 | D15: "Cudjoe, Nanny, Sally, Peggy and Coobah in the garden" | E15: CUDJOE (P52) NANNY (P15) SALLY (P17) PEGGY (P19) MOLIA (P1) | F15: GARDENING/AGRICULTURE | G15: COOBAH | H15: BREADNUT ISLAND PEN | I15: L3 | J15: AM
A16: E10 | B16: IMG 55, P.50 | C16: March 21, 1768 | D16: "Cudjoe, Coobah, Peggy, Sally, and Nanny carrying my logwood down from home to Mr. Say's Ranch Side" | E16: CUDJOE (P52) NANNY (P15) SALLY (P17) PEGGY (P19) MOLIA (P1) | F16: LABOR | G16: COOBAH | H16: BREADNUT ISLAND PEN CABARITTA ESTATE | I16: L3 L8 | J16: AM
A17: E10 | B17: IMG 58, P.53 | C17: March 28, 1768 | D17: "Thirteen of my Negroes at Forest's as Coobah is gone there now." | E17: MOLIA (P1) | F17: LABOR | G17: COOBAH | H17: MASEMURE ESTATE | I17: L6 | J17: AM
A18: E11 | B18: IMG 6, P.1 | C18: January 1, 1769 | D18: Negroes 26 (Coobah's Silvia being dead since last June." (?) | E18: SILVIA (P2) | F18: INVENTORY/RECORDS
A19: E5 | B19: IMG 13, P.8 | C19: January 9. 1769 | D19: "Sent John to Mr. Hughes to school, this morning. After John was gone this morning, a green sediment was perceived in his chamberpot, like gall; but he makes no complaint." | E19: JOHN (P9) | F19: ILLNESS | G19: MULATTO JOHN | H19: BREADNUT ISLAND PEN | I19: L3 | J19: AM
A20: E6 | B20: IMG 30, P. 25 | C20: February 6, 1769 | D20: "As Mulatto John come home on Saturday to see his momma etc, sent him to school again this morning and gave a Bible with him." | E20: JOHN (P9); PHIBBAH (P7) | F20: SCHOOL | G20: MULATTO JOHN | H20: BREADNUT ISLAND PEN | J20: AM
A21: E12 | B21: IMG 53 | C21: March 20, 1769 | D21: "Lincoln come home this evening to look for Coobah, who is not at work. Gave him a bitt." | E21: LINCOLN (P24) MOLIA (P1) | F21: ESCAPE/TRUANCY | G21: COOBAH | H21: BREADNUT ISLAND PEN | I21: L3 | J21: PM
A22: E12 | B22: IMG 54 | C22: March 21, 1769 | D22: "This morning Lincoln come without finding Coobah, sent him to Bluecastle to see if she be not gone to work." | E22: LINCOLN (P24) MOLIA (P1) | F22: ESCAPE/TRUANCY | G22: COOBAH | H22: BREADNUT ISLAND PEN BLUECASTLE ESTATE | I22: L3 L14 | J22: AM
A23: E7 | B23: IMG 57, P.52 | C23: March 25, 1769 | D23: "I continue much the same.Phibbah still continues very ill, gave her 2 nervous pills, morning and evening. John slept with me." | E23: JOHN (P9); PHIBBAH (P7); | F23: ILLNESS | G23: MULATTO JOHN | H23: BREADNUT ISLAND PEN | I23: L3 | J23: AM/PM
A24: E12 | B24: IMG 57, P. 52 | C24: March 26, 1769 | D24: "Served my Negroes 20 bitts. Lincoln and Coobah not come for their allowance." | E24: LINCOLN (P24) MOLIA (P1) | F24: ESCAPE/TRUANCY | G24: COOBAH | H24: BREADNUT ISLAND PEN | I24: L3 | J24: AM
A25: E8 | B25: IMG 57, P.52 | C25: March 27, 1769 | D25: "Last night John lay in my bed again, and he p...d it." | E25: JOHN (P9) | F25: ILLNESS | G25: MULATTO JOHN | H25: BREADNUT ISLAND PEN | I25: L3 | J25: PM
A26: E13 | B26: IMG 109, P.104 | C26: June 30, 1770 | D26: "Coobah wanting, sent Solon to look [for] her, but he found nothing of her." | E26: MOLIA (P1) SOLON (26) | F26: ESCAPE/TRUANCY | G26: COOBAH | H26: WILDERNESS UNKNOWN | I26: L15 L0 | J26: AM | K26: "Mod. Breezes, SE and at times cloudy. PM: Most partly cloudy, a showed of rain, lightning at a distance, at night lightning." (IMG 348, p.25)
A27: E13 | B27: IMG 111, P.106 | C27: July 2, 1770 | D27: "Coobah runaway, gave Lincoln a ticket to go look for her." | E27: LINCOLN (P24) MOLIA (P1) | F27: ESCAPE/TRUANCY | G27: COOBAH | H27: WILDERNESS UNKNOWN | I27: L15 L0 | J27: AM | K27: July 1: "Mod. Breezes SE and at times cloudy. P.M.: A shower of rain, with thunder and lightning." July 2: Light wind, variable and at times cloudy. PM: Thunder remote at night, Lightning." (IMG 348, p.25)
A28: E13 | B28: IMG 112, P.107 | C28: July 2, 1770 | D28: "In the evening received a note from Mr. James Lymborner by Cromwell, with my Coobah. Put her in the bilboes. Wrote to Mr. Lymborner and gave Cromwell 2 bitts." | E28: MOLIA (P1) | F28: ESCAPE/TRUANCY | G28: COOBAH | H28: BREADNUT ISLAND PEN | I28: L3 | J28: PM
A29: E13 | B29: IMG 112, P.107 | C29: July 3, 1770 | D29: "Took Coobah out of the bilboes, flogged her and put on a collar and chain and sent her to the rest, who are clearing the pasture." | E29: MOLIA (P1) | F29: PUNISHMENT | G29: COOBAH | H29: BREADNUT ISLAND PEN WILDERNESS | I29: L3 L15 | J29: AM
A30: E14 | B30: IMG 115 | C30: July 6, 1770 | D30: "Coobah wanting, but about 4 o'clock Jimmy & Damsel coming home with water from Barclay's river met her going that way and brought her back. Flogged her well and brandmarked her in the forehead. She has broke open Mr. Say's Nancy's house since noon, stolenr ice, calbasas &..." | E30: MOLIA (P1) JIMMY (P54) DAMSEL (P34) | F30: ESCAPE/TRUANCY | G30: COOBAH | H30: BREADNUT ISLAND PEN BARCLAY'S RIVER CABARITTA ESTATE | I30: L3 L8 L16 | J30: PM | K30: "Light winds variable and at times cloudy. P.M.: Most partly cloudy, a few drops of rain with Thunder and lightning."
A31: E14 | B31: IMG 115 | C31: July 6, 1770 | D31: "Coobah wanting, but about 4 o'clock Jimmy & Damsel coming home with water from Barclay's river met her going that way and brought her back. Flogged her well and brandmarked her in the forehead. She has broke open Mr. Say's Nancy's house since noon, stolenr ice, calbasas &..." | E31: MOLIA (P1) JIMMY (P54) DAMSEL (P34) | F31: PUNISHMENT | G31: COOBAH | H31: BREADNUT ISLAND PEN BARCLAY'S RIVER CABARITTA ESTATE | I31: L3 L8 L16 | J31: PM | K31: "Light winds variable and at times cloudy. P.M.: Most partly cloudy, a few drops of rain with Thunder and lightning."
A32: E16 | B32: IMG 118, P.113 | C32: July 11, 1770 | D32: "Coobah wanting this morning. Sent Solon to look [for] her, and in the evening, he brought her. She had been in Egypt Canes." | E32: MOLIA (P1) JIMMY (P54) | F32: ESCAPE/TRUANCY | G32: COOBAH | H32: BREADNUT ISLAND PEN EGYPT ESTATE | I32: L3 L1 | J32: AM/PM
A33: E17 | B33: IMG 125, P.120 | C33: July 26, 1770 | D33: "Found Coobah had got her collar loose, so took it off her for good: once more." | E33: MOLIA (P1) | F33: PUNISHMENT | G33: COOBAH | H33: BREADNUT ISLAND PEN | I33: L3 | J33: AM
A34: EVENT ID | B34: ARCHIVE ID(S) | C34: DATE(S) | D34: EVENT DESCRIPTION | E34: PERSON IDS | F34: EVENT TYPE | G34: ALTERNATE NAMES | H34: LOCATION | I34: LOCATION ID | J34: TIME OF DAY (AM/PM) | K34: WEATHER | L34: SPECIAL SKILL
